{
  "generatedAt": "2026-07-19T13:58:07.282941Z",
  "sections": [
    {
      "section": "Bhilai",
      "count": 5,
      "items": [
        {
          "videoId": "mq2tEZpxclc",
          "title": "Bhilai का शीतला तालाब आखिर किसके भरोसे?",
          "description": "news #bhilainews #kpnewsbhilai #kpnewscg #kpnews #cgnews #chhattisgarh #chhattisgarhnews #bhilai #bhilaidurg ...",
          "channelTitle": "KPNews",
          "publishedAt": "2026-07-19T13:02:13Z",
          "thumbnail": "https://i.ytimg.com/vi/mq2tEZpxclc/hqdefault.jpg",
          "durationSeconds": 82,
          "durationFormatted": "01:22",
          "views": 81,
          "likes": 0,
          "videoType": "VOD",
          "genre": "General"
        },
        {
          "videoId": "WZ2HazVBxv0",
          "title": "Bhilai में भगवान जगन्नाथ की भव्य रथयात्रा, हजारों श्रद्धालुओं ने खींचा रथ || @KPNews_",
          "description": "news #bhilainews #kpnewsbhilai #kpnewscg #kpnews #cgnews #chhattisgarh #chhattisgarhnews #bhilai #bhilaidurg ...",
          "channelTitle": "KPNews",
          "publishedAt": "2026-07-19T13:02:05Z",
          "thumbnail": "https://i.ytimg.com/vi/WZ2HazVBxv0/hqdefault.jpg",
          "durationSeconds": 72,
          "durationFormatted": "01:12",
          "views": 23,
          "likes": 0,
          "videoType": "VOD",
          "genre": "General"
        },
        {
          "videoId": "W3Np4lT-TSQ",
          "title": "Bhilai का शीतला तालाब बदहाल! नशाखोरी रोकी तो कर दी मारपीट!",
          "description": "news #bhilainews #kpnewsbhilai #kpnewscg #kpnews #cgnews #chhattisgarh #chhattisgarhnews #bhilai #bhilaidurg ...",
          "channelTitle": "KPNews",
          "publishedAt": "2026-07-19T13:01:53Z",
          "thumbnail": "https://i.ytimg.com/vi/W3Np4lT-TSQ/hqdefault.jpg",
          "durationSeconds": 122,
          "durationFormatted": "02:02",
          "views": 60,
          "likes": 0,
          "videoType": "VOD",
          "genre": "Crime"
        },
        {
          "videoId": "02UVN2rgetQ",
          "title": "Bhilai में खुली नाली बनी मौt का जाल...घर लौट रहे बुजुर्ग की दर्दनाक मौt! || KP NEWS || Jaanvi sahu",
          "description": "news #bhilainews #kpnewsbhilai #kpnewscg #kpnews #cgnews #chhattisgarh #chhattisgarhnews #bhilai #bhilaidurg ...",
          "channelTitle": "KPNews",
          "publishedAt": "2026-07-19T09:35:43Z",
          "thumbnail": "https://i.ytimg.com/vi/02UVN2rgetQ/hqdefault.jpg",
          "durationSeconds": 562,
          "durationFormatted": "09:22",
          "views": 1551,
          "likes": 0,
          "videoType": "VOD",
          "genre": "General"
        },
        {
          "videoId": "EklBm65OFyg",
          "title": "Bhilai: युवक पर चा.कू से हमला, चश्मदीद और परिजनों ने कही ये बात || KP NEWS || Faizan",
          "description": "news #bhilainews #kpnewsbhilai #kpnewscg #kpnews #cgnews #chhattisgarh #chhattisgarhnews #bhilai #bhilaidurg ...",
          "channelTitle": "KPNews",
          "publishedAt": "2026-07-18T15:30:01Z",
          "thumbnail": "https://i.ytimg.com/vi/EklBm65OFyg/hqdefault.jpg",
          "durationSeconds": 644,
          "durationFormatted": "10:44",
          "views": 3977,
          "likes": 0,
          "videoType": "VOD",
          "genre": "Crime"
        }
      ],
      "sectionIndex": 0
    },
    {
      "section": "Live",
      "count": 1,
      "items": [
        {
          "videoId": "VnfZRdeTX2w",
          "title": "वैशालीनगर को लेकर क्या है Rikesh Sen का विजन? विधायक ने बताया पूरा रोडमैप।Vidhayak Ji Live",
          "description": "IBC24, वैशालीनगर को लेकर क्या है Rikesh Sen का विजन? विधायक ने बताया पूरा ...",
          "channelTitle": "IBC24",
          "publishedAt": "2026-07-19T13:41:56Z",
          "thumbnail": "https://i.ytimg.com/vi/VnfZRdeTX2w/hqdefault_live.jpg",
          "durationSeconds": 0,
          "durationFormatted": "LIVE",
          "views": 43,
          "likes": 0,
          "videoType": "LIVE",
          "genre": "Live"
        }
      ],
      "sectionIndex": 0
    },
    {
      "section": "Scheduled",
      "count": 0,
      "items": [],
      "sectionIndex": 0
    },
    {
      "section": "General",
      "count": 38,
      "items": [
        {
          "videoId": "hwLWGH1v4Wg",
          "title": "UCC पर कैबिनेट की मुहर.. अब सदन पर नजर | UCC in MP। MP KI Baat। शह मात The Big Debate",
          "description": "IBC24, UCC पर कैबिनेट की मुहर.. अब सदन पर नजर | UCC in MP। MP KI Baat। शह मात The Big ...",
          "channelTitle": "IBC24",
          "publishedAt": "2026-07-19T13:53:49Z",
          "thumbnail": "https://i.ytimg.com/vi/hwLWGH1v4Wg/hqdefault.jpg",
          "durationSeconds": 1261,
          "durationFormatted": "21:01",
          "views": 506,
          "likes": 0,
          "videoType": "VOD",
          "genre": "General"
        },
        {
          "videoId": "05e-g0JjENk",
          "title": "vivo X300 Ultra &amp; X300 FE – अब और भी शानदार ऑफर्स के साथ! ✨",
          "description": "इस सीज़न अपने पसंदीदा vivo X300 Ultra या vivo X300 FE को घर लाने का सही मौका।",
          "channelTitle": "KPNews",
          "publishedAt": "2026-07-19T13:36:20Z",
          "thumbnail": "https://i.ytimg.com/vi/05e-g0JjENk/hqdefault.jpg",
          "durationSeconds": 93,
          "durationFormatted": "01:33",
          "views": 8,
          "likes": 0,
          "videoType": "VOD",
          "genre": "General"
        },
        {
          "videoId": "BQynkEEBBDM",
          "title": "Solar Pannel लगवाने से पहले ये देखें..सस्ती नहीं, सुरक्षित क्वालिटी चुनें!",
          "description": "सोलर पैनल लगवाने से पहले ये देखें! सस्ती नहीं, सुरक्षित क्वालिटी ...",
          "channelTitle": "KPNews",
          "publishedAt": "2026-07-19T13:36:17Z",
          "thumbnail": "https://i.ytimg.com/vi/BQynkEEBBDM/hqdefault.jpg",
          "durationSeconds": 96,
          "durationFormatted": "01:36",
          "views": 40,
          "likes": 0,
          "videoType": "VOD",
          "genre": "General"
        },
        {
          "videoId": "lxC7cKiguc4",
          "title": "Ayodhya News: Mahant Dinendra Das हटाए गए। निर्मोही अखाड़ा सुप्रीम कोर्ट पहुंचा",
          "description": "IBC24, Ayodhya News: Mahant Dinendra Das हटाए गए। निर्मोही अखाड़ा सुप्रीम कोर्ट ...",
          "channelTitle": "IBC24",
          "publishedAt": "2026-07-19T13:29:41Z",
          "thumbnail": "https://i.ytimg.com/vi/lxC7cKiguc4/hqdefault.jpg",
          "durationSeconds": 109,
          "durationFormatted": "01:49",
          "views": 24,
          "likes": 0,
          "videoType": "VOD",
          "genre": "General"
        },
        {
          "videoId": "ONu7yUuksg4",
          "title": "Guru Ast 2026: किन राशियों पर पड़ेगा असर? जानिए आसान ज्योतिष उपाय। SITARE HAMARE",
          "description": "IBC24, Guru Ast 2026: किन राशियों पर पड़ेगा असर? जानिए आसान ज्योतिष उपाय।",
          "channelTitle": "IBC24",
          "publishedAt": "2026-07-19T13:22:01Z",
          "thumbnail": "https://i.ytimg.com/vi/ONu7yUuksg4/hqdefault.jpg",
          "durationSeconds": 823,
          "durationFormatted": "13:43",
          "views": 35,
          "likes": 0,
          "videoType": "VOD",
          "genre": "General"
        },
        {
          "videoId": "TrNdnOZtLR0",
          "title": "हाथियों के रास्ते हाईटेंशन..सिस्टम क्यों साइलेंट? हाथियों के जंगल में हाइटेशन का खेल! Raigarh News",
          "description": "IBC24, हाथियों के रास्ते हाईटेंशन..सिस्टम क्यों साइलेंट? हाथियों के ...",
          "channelTitle": "IBC24",
          "publishedAt": "2026-07-19T13:21:21Z",
          "thumbnail": "https://i.ytimg.com/vi/TrNdnOZtLR0/hqdefault.jpg",
          "durationSeconds": 815,
          "durationFormatted": "13:35",
          "views": 60,
          "likes": 0,
          "videoType": "VOD",
          "genre": "General"
        },
        {
          "videoId": "mq2tEZpxclc",
          "title": "Bhilai का शीतला तालाब आखिर किसके भरोसे?",
          "description": "news #bhilainews #kpnewsbhilai #kpnewscg #kpnews #cgnews #chhattisgarh #chhattisgarhnews #bhilai #bhilaidurg ...",
          "channelTitle": "KPNews",
          "publishedAt": "2026-07-19T13:02:13Z",
          "thumbnail": "https://i.ytimg.com/vi/mq2tEZpxclc/hqdefault.jpg",
          "durationSeconds": 82,
          "durationFormatted": "01:22",
          "views": 81,
          "likes": 0,
          "videoType": "VOD",
          "genre": "General"
        },
        {
          "videoId": "WZ2HazVBxv0",
          "title": "Bhilai में भगवान जगन्नाथ की भव्य रथयात्रा, हजारों श्रद्धालुओं ने खींचा रथ || @KPNews_",
          "description": "news #bhilainews #kpnewsbhilai #kpnewscg #kpnews #cgnews #chhattisgarh #chhattisgarhnews #bhilai #bhilaidurg ...",
          "channelTitle": "KPNews",
          "publishedAt": "2026-07-19T13:02:05Z",
          "thumbnail": "https://i.ytimg.com/vi/WZ2HazVBxv0/hqdefault.jpg",
          "durationSeconds": 72,
          "durationFormatted": "01:12",
          "views": 23,
          "likes": 0,
          "videoType": "VOD",
          "genre": "General"
        },
        {
          "videoId": "kgBjEZCztS8",
          "title": "गरियाबंद के आमामोरा में किसानों को अजीबो गरीब मुआवजा, फायर वाचर ने भी भांजी मारी | CG Bhaskar",
          "description": "गरियाबंद के आमामोरा में किसानों को अजीबो गरीब मुआवजा, फायर वाचर ने ...",
          "channelTitle": "CG Bhaskar",
          "publishedAt": "2026-07-19T13:00:00Z",
          "thumbnail": "https://i.ytimg.com/vi/kgBjEZCztS8/hqdefault.jpg",
          "durationSeconds": 701,
          "durationFormatted": "11:41",
          "views": 12,
          "likes": 1,
          "videoType": "VOD",
          "genre": "General"
        },
        {
          "videoId": "wOMNz--HJf8",
          "title": "भारत ग्रुप ने कहा-छवि खराब करने वाले कानूनी कार्रवाई के लिए तैयार रहें (ADVT) | CG Bhaskar",
          "description": "भारत ग्रुप ने कहा-छवि खराब करने वाले कानूनी कार्रवाई के लिए तैयार ...",
          "channelTitle": "CG Bhaskar",
          "publishedAt": "2026-07-19T12:47:03Z",
          "thumbnail": "https://i.ytimg.com/vi/wOMNz--HJf8/hqdefault.jpg",
          "durationSeconds": 179,
          "durationFormatted": "02:59",
          "views": 30,
          "likes": 3,
          "videoType": "VOD",
          "genre": "General"
        },
        {
          "videoId": "mFs5ooOceMU",
          "title": "Bilaspur के नोबल अस्पताल पर गंभीर आरोप, पूरे पैसे लेकर इलाज में देरी। जानें पूरा मामला | CG Bhaskar",
          "description": "बिलासपुर के महाराणा प्रताप मार्ग स्थित नोबल हॉस्पिटल पर इलाज में ...",
          "channelTitle": "CG Bhaskar",
          "publishedAt": "2026-07-19T12:00:28Z",
          "thumbnail": "https://i.ytimg.com/vi/mFs5ooOceMU/hqdefault.jpg",
          "durationSeconds": 406,
          "durationFormatted": "06:46",
          "views": 130,
          "likes": 6,
          "videoType": "VOD",
          "genre": "General"
        },
        {
          "videoId": "4YkPPuFRMzk",
          "title": "भिलाई की सड़कों पर बारिश के साथ भुट्टों की बहार, सेहत भी बनाता है। khush | CG Bhaskar",
          "description": "भिलाई की सड़कों पर बारिश के साथ भुट्टों की बहार, सेहत भी बनाता है। khush ...",
          "channelTitle": "CG Bhaskar",
          "publishedAt": "2026-07-19T11:00:25Z",
          "thumbnail": "https://i.ytimg.com/vi/4YkPPuFRMzk/hqdefault.jpg",
          "durationSeconds": 646,
          "durationFormatted": "10:46",
          "views": 136,
          "likes": 6,
          "videoType": "VOD",
          "genre": "General"
        },
        {
          "videoId": "IShrdxkc1UU",
          "title": "तेज बारिश में घरों से निकले &#39;कॉकरोच&#39; कर रहे प्रदर्शन | CG Bhaskar",
          "description": "तेज बारिश में घरों से निकले 'कॉकरोच' कर रहे प्रदर्शन | CG Bhaskar राजधानी ...",
          "channelTitle": "CG Bhaskar",
          "publishedAt": "2026-07-19T10:32:36Z",
          "thumbnail": "https://i.ytimg.com/vi/IShrdxkc1UU/hqdefault.jpg",
          "durationSeconds": 140,
          "durationFormatted": "02:20",
          "views": 106,
          "likes": 5,
          "videoType": "VOD",
          "genre": "General"
        },
        {
          "videoId": "UmbD1Mqy_PI",
          "title": "खेतों में दिखा गाँव की महिलाओं का अनोखा स्वैग",
          "description": "खेतों में दिखा गाँव की महिलाओं का अनोखा स्वैग Join this channel to get access to the ...",
          "channelTitle": "Bhilai Times",
          "publishedAt": "2026-07-19T10:00:24Z",
          "thumbnail": "https://i.ytimg.com/vi/UmbD1Mqy_PI/hqdefault.jpg",
          "durationSeconds": 141,
          "durationFormatted": "02:21",
          "views": 1501,
          "likes": 56,
          "videoType": "VOD",
          "genre": "General"
        },
        {
          "videoId": "0gx0T_6zkW0",
          "title": "Mohan Cabinet Big Decision: मोहन कैबिनेट का बड़ा फैसला। UCC ड्राफ्ट को कैबिनेट में मिली मंजूरी",
          "description": "IBC24, Mohan Cabinet Big Decision: मोहन कैबिनेट का बड़ा फैसला। UCC ड्राफ्ट को ...",
          "channelTitle": "IBC24",
          "publishedAt": "2026-07-19T09:44:56Z",
          "thumbnail": "https://i.ytimg.com/vi/0gx0T_6zkW0/hqdefault.jpg",
          "durationSeconds": 680,
          "durationFormatted": "11:20",
          "views": 473,
          "likes": 0,
          "videoType": "VOD",
          "genre": "General"
        },
        {
          "videoId": "02UVN2rgetQ",
          "title": "Bhilai में खुली नाली बनी मौt का जाल...घर लौट रहे बुजुर्ग की दर्दनाक मौt! || KP NEWS || Jaanvi sahu",
          "description": "news #bhilainews #kpnewsbhilai #kpnewscg #kpnews #cgnews #chhattisgarh #chhattisgarhnews #bhilai #bhilaidurg ...",
          "channelTitle": "KPNews",
          "publishedAt": "2026-07-19T09:35:43Z",
          "thumbnail": "https://i.ytimg.com/vi/02UVN2rgetQ/hqdefault.jpg",
          "durationSeconds": 562,
          "durationFormatted": "09:22",
          "views": 1551,
          "likes": 0,
          "videoType": "VOD",
          "genre": "General"
        },
        {
          "videoId": "7m9f5swz-HE",
          "title": "क्या Radiation Therapy से शरीर जल जाता है? जानिए Dr. Rahul Swaroop Singh की राय | Health Guru",
          "description": "IBC24, क्या Radiation Therapy से शरीर जल जाता है? जानिए Dr. Rahul Swaroop Singh की राय | Health ...",
          "channelTitle": "IBC24",
          "publishedAt": "2026-07-19T09:33:31Z",
          "thumbnail": "https://i.ytimg.com/vi/7m9f5swz-HE/hqdefault.jpg",
          "durationSeconds": 1487,
          "durationFormatted": "24:47",
          "views": 215,
          "likes": 0,
          "videoType": "VOD",
          "genre": "General"
        },
        {
          "videoId": "BiXkzeRilfY",
          "title": "&#39;प्रतियोगी परीक्षा में गड़बड़ी..महामारी की तरह&#39;। NEET Paper Leak पर Charandas Mahant का बड़ा बयान",
          "description": "IBC24, 'प्रतियोगी परीक्षा में गड़बड़ी..महामारी की तरह'। NEET Paper Leak पर ...",
          "channelTitle": "IBC24",
          "publishedAt": "2026-07-19T09:25:31Z",
          "thumbnail": "https://i.ytimg.com/vi/BiXkzeRilfY/hqdefault.jpg",
          "durationSeconds": 75,
          "durationFormatted": "01:15",
          "views": 75,
          "likes": 0,
          "videoType": "VOD",
          "genre": "General"
        },
        {
          "videoId": "wrq6zwdaSYc",
          "title": "Raipur Youth Protest News: Sonam Wangchuk के समर्थन में सड़कों पर उतरे रायपुर के युवा। देखिए..",
          "description": "IBC24, Raipur Youth Protest News: Sonam Wangchuk के समर्थन में सड़कों पर उतरे रायपुर के ...",
          "channelTitle": "IBC24",
          "publishedAt": "2026-07-19T09:21:06Z",
          "thumbnail": "https://i.ytimg.com/vi/wrq6zwdaSYc/hqdefault.jpg",
          "durationSeconds": 59,
          "durationFormatted": "00:59",
          "views": 1899,
          "likes": 0,
          "videoType": "VOD",
          "genre": "General"
        },
        {
          "videoId": "hU6cYLUSSDc",
          "title": "सुपेला में दर्दनाक हाdसा खुले नाले में घुसी स्कूटी और | CG Bhaskar",
          "description": "सुपेला में दर्दनाक हाdसा खुले नाले में घुसी स्कूटी और | CG Bhaskar भिलाई ...",
          "channelTitle": "CG Bhaskar",
          "publishedAt": "2026-07-19T09:07:01Z",
          "thumbnail": "https://i.ytimg.com/vi/hU6cYLUSSDc/hqdefault.jpg",
          "durationSeconds": 148,
          "durationFormatted": "02:28",
          "views": 631,
          "likes": 41,
          "videoType": "VOD",
          "genre": "General"
        },
        {
          "videoId": "G1T_iutmLSw",
          "title": "Ram Mandir Trust Meeting: 22 जुलाई को राम मंदिर ट्रस्ट की बड़ी बैठक। हो सकते हैं ये बड़े ऐलान..",
          "description": "IBC24, Ram Mandir Trust Meeting: 22 जुलाई को राम मंदिर ट्रस्ट की बड़ी बैठक। हो सकते ...",
          "channelTitle": "IBC24",
          "publishedAt": "2026-07-19T09:01:11Z",
          "thumbnail": "https://i.ytimg.com/vi/G1T_iutmLSw/hqdefault.jpg",
          "durationSeconds": 130,
          "durationFormatted": "02:10",
          "views": 73,
          "likes": 0,
          "videoType": "VOD",
          "genre": "General"
        },
        {
          "videoId": "dW-I_Jz6ZCE",
          "title": "72 घंटे में सुलझा &#39;ब्लाइंड मर्डR&#39;: पुलिस डॉग &#39;रूबी&#39; ने खोले सारे राज...",
          "description": "72 घंटे में सुलझा 'ब्लाइंड मर्डR': पुलिस डॉग 'रूबी' ने खोले सारे राज.",
          "channelTitle": "Bhilai Times",
          "publishedAt": "2026-07-19T09:00:39Z",
          "thumbnail": "https://i.ytimg.com/vi/dW-I_Jz6ZCE/hqdefault.jpg",
          "durationSeconds": 180,
          "durationFormatted": "03:00",
          "views": 4878,
          "likes": 98,
          "videoType": "VOD",
          "genre": "General"
        },
        {
          "videoId": "815TMjcX60g",
          "title": "Hamara Uttar Pradesh । उत्तरप्रदेश की आज की बड़ी खबरें। 19 July 2026 | UP Latest News Today",
          "description": "IBC24, Hamara Uttar Pradesh । उत्तरप्रदेश की आज की बड़ी खबरें। 19 July 2026 | UP Latest News ...",
          "channelTitle": "IBC24",
          "publishedAt": "2026-07-19T08:51:41Z",
          "thumbnail": "https://i.ytimg.com/vi/815TMjcX60g/hqdefault.jpg",
          "durationSeconds": 895,
          "durationFormatted": "14:55",
          "views": 96,
          "likes": 0,
          "videoType": "VOD",
          "genre": "General"
        },
        {
          "videoId": "5PCwD9qD5qE",
          "title": "AC का रंग सफेद ही क्यों? जानिए असली वजह | CG Bhaskar",
          "description": "गर्मी के मौसम में लगभग हर घर में AC का इस्तेमाल होता है, लेकिन क्या ...",
          "channelTitle": "CG Bhaskar",
          "publishedAt": "2026-07-19T08:45:13Z",
          "thumbnail": "https://i.ytimg.com/vi/5PCwD9qD5qE/hqdefault.jpg",
          "durationSeconds": 97,
          "durationFormatted": "01:37",
          "views": 247,
          "likes": 13,
          "videoType": "VOD",
          "genre": "General"
        },
        {
          "videoId": "3akNF5ri7u0",
          "title": "Mohan Cabinet Meeting Decision LIVE: मोहन कैबिनेट की बैठक खत्म। UCC विधेयक को कैबिनेट की मुहर",
          "description": "IBC24, Mohan Cabinet Meeting Decision LIVE: मोहन कैबिनेट की बैठक खत्म। UCC विधेयक को ...",
          "channelTitle": "IBC24",
          "publishedAt": "2026-07-19T08:43:41Z",
          "thumbnail": "https://i.ytimg.com/vi/3akNF5ri7u0/hqdefault.jpg",
          "durationSeconds": 1578,
          "durationFormatted": "26:18",
          "views": 289,
          "likes": 0,
          "videoType": "VOD",
          "genre": "General"
        },
        {
          "videoId": "tavuuhEso3I",
          "title": "FIFA World Cup 2026 Final: Spain vs Argentina..कौन बनेगा नया World Champion? FIFA WC 2026 Final",
          "description": "IBC24, FIFA World Cup 2026 Final: Spain vs Argentina..कौन बनेगा नया World Champion? FIFA WC 2026 Final ...",
          "channelTitle": "IBC24",
          "publishedAt": "2026-07-19T08:04:39Z",
          "thumbnail": "https://i.ytimg.com/vi/tavuuhEso3I/hqdefault.jpg",
          "durationSeconds": 131,
          "durationFormatted": "02:11",
          "views": 7385,
          "likes": 0,
          "videoType": "VOD",
          "genre": "General"
        },
        {
          "videoId": "suVQYv4g18E",
          "title": "बारिश में पेड़ के नीचे खड़े  होने वाले सावधान! बिजली  गिरने से दो बच्चों की....",
          "description": "बारिश में पेड़ के नीचे खड़े होने वाले सावधान! बिजली गिरने से दो ...",
          "channelTitle": "Bhilai Times",
          "publishedAt": "2026-07-19T07:00:32Z",
          "thumbnail": "https://i.ytimg.com/vi/suVQYv4g18E/hqdefault.jpg",
          "durationSeconds": 98,
          "durationFormatted": "01:38",
          "views": 5674,
          "likes": 269,
          "videoType": "VOD",
          "genre": "General"
        },
        {
          "videoId": "8jJegNN3i0M",
          "title": "Breaking News : अमित भटनागर गिरफ्तार! केन-बेतवा आंदोलन पर पुलिस का बड़ा एक्शन | India News MP |",
          "description": "छतरपुर में केन-बेतवा लिंक परियोजना के विरोध में चल रहे चिता आंदोलन ...",
          "channelTitle": "India News Madhya Pradesh Chhattisgarh",
          "publishedAt": "2026-07-19T06:33:33Z",
          "thumbnail": "https://i.ytimg.com/vi/8jJegNN3i0M/hqdefault.jpg",
          "durationSeconds": 331,
          "durationFormatted": "05:31",
          "views": 72,
          "likes": 1,
          "videoType": "VOD",
          "genre": "General"
        },
        {
          "videoId": "9WF78qnekcg",
          "title": "MP News : बारिश को लेकर IMD का बड़ा अपडेट! MP के 22 जिले हाई अलर्ट पर |",
          "description": "मध्य प्रदेश में मानसून एक बार फिर सक्रिय हो गया है। पश्चिम बंगाल के ...",
          "channelTitle": "India News Madhya Pradesh Chhattisgarh",
          "publishedAt": "2026-07-19T06:10:50Z",
          "thumbnail": "https://i.ytimg.com/vi/9WF78qnekcg/hqdefault.jpg",
          "durationSeconds": 205,
          "durationFormatted": "03:25",
          "views": 40,
          "likes": 0,
          "videoType": "VOD",
          "genre": "General"
        },
        {
          "videoId": "kArFrwiCVV4",
          "title": "शिक्षक ने CG Bhasker को कविता पढ़कर जताया विरोध | CG Bhaskar",
          "description": "शिक्षक ने CG Bhasker को कविता पढ़कर जताया विरोध | CG Bhaskar राज्य अतिथि ...",
          "channelTitle": "CG Bhaskar",
          "publishedAt": "2026-07-19T03:30:28Z",
          "thumbnail": "https://i.ytimg.com/vi/kArFrwiCVV4/hqdefault.jpg",
          "durationSeconds": 128,
          "durationFormatted": "02:08",
          "views": 215,
          "likes": 10,
          "videoType": "VOD",
          "genre": "General"
        },
        {
          "videoId": "PWSux-wIXpY",
          "title": "बुड्ढी के बाल देख आई बचपन की याद | CG Bhaskar",
          "description": "सोनपापड़ी बेचते हुए अंकल ने बताया अपना अनुभव। * अब कम हो चुकी है ...",
          "channelTitle": "CG Bhaskar",
          "publishedAt": "2026-07-19T02:30:05Z",
          "thumbnail": "https://i.ytimg.com/vi/PWSux-wIXpY/hqdefault.jpg",
          "durationSeconds": 155,
          "durationFormatted": "02:35",
          "views": 461,
          "likes": 27,
          "videoType": "VOD",
          "genre": "General"
        },
        {
          "videoId": "nyPMi-UMrMQ",
          "title": "Bilaspur Ground Report | इसलिए डूब गया शहर | कौन है जिम्मेदार | Pranshu Kshatriya |",
          "description": "Bilaspur Ground Report | इसलिए डूब गया शहर | कौन है जिम्मेदार | Report/Story: Pranshu Kshatriya ...",
          "channelTitle": "Bhilai Times",
          "publishedAt": "2026-07-19T02:00:38Z",
          "thumbnail": "https://i.ytimg.com/vi/nyPMi-UMrMQ/hqdefault.jpg",
          "durationSeconds": 760,
          "durationFormatted": "12:40",
          "views": 10169,
          "likes": 210,
          "videoType": "VOD",
          "genre": "General"
        },
        {
          "videoId": "tsfq_s1PVdY",
          "title": "Chhattisgarh News Today | 19 जुलाई 2026 छत्तीसगढ़ की फटाफट बड़ी खबरें, CG Samachar, Media CG News",
          "description": "Chhattisgarh News Today | 19 जुलाई 2026 छत्तीसगढ़ की फटाफट बड़ी खबरें, CG Samachar, Media ...",
          "channelTitle": "Media Chhattisgarh",
          "publishedAt": "2026-07-18T23:20:26Z",
          "thumbnail": "https://i.ytimg.com/vi/tsfq_s1PVdY/hqdefault.jpg",
          "durationSeconds": 1076,
          "durationFormatted": "17:56",
          "views": 27084,
          "likes": 439,
          "videoType": "VOD",
          "genre": "General"
        },
        {
          "videoId": "x35QNFu2ing",
          "title": "बिलासपुर में बाढ़ का कहर! घर बने टापू, सड़कों पर दौड़ी नाव  #BilaspurFlood #HeavyRain #FloodAlert",
          "description": "बिलासपुर में बाढ़ का कहर! घर बने टापू, सड़कों पर दौड़ी नाव #Bilaspur ...",
          "channelTitle": "Vayam Chhattisgarh",
          "publishedAt": "2026-07-18T16:40:55Z",
          "thumbnail": "https://i.ytimg.com/vi/x35QNFu2ing/hqdefault.jpg",
          "durationSeconds": 54,
          "durationFormatted": "00:54",
          "views": 810,
          "likes": 8,
          "videoType": "VOD",
          "genre": "General"
        },
        {
          "videoId": "kh3APyJm5XQ",
          "title": "ऑटो चालक ने महिला के सोने के जेवर किए पार, देखें CCTV फुटेज  | CG Bhaskar",
          "description": "ऑटो चालक ने महिला के सोने के जेवर किए पार, देखें CCTV फुटेज | CG Bhaskar ...",
          "channelTitle": "CG Bhaskar",
          "publishedAt": "2026-07-18T16:15:03Z",
          "thumbnail": "https://i.ytimg.com/vi/kh3APyJm5XQ/hqdefault.jpg",
          "durationSeconds": 86,
          "durationFormatted": "01:26",
          "views": 706,
          "likes": 14,
          "videoType": "VOD",
          "genre": "General"
        },
        {
          "videoId": "IfnCRmGiMjE",
          "title": "ड्यूटी जाने के दौरान अतिथि शिक्षक के कटे हाथ… | CG Bhaskar",
          "description": "ड्यूटी जाने के दौरान अतिथि शिक्षक के कटे हाथ… | CG Bhaskar ड्यूटी जा रही ...",
          "channelTitle": "CG Bhaskar",
          "publishedAt": "2026-07-18T15:30:33Z",
          "thumbnail": "https://i.ytimg.com/vi/IfnCRmGiMjE/hqdefault.jpg",
          "durationSeconds": 160,
          "durationFormatted": "02:40",
          "views": 1867,
          "likes": 42,
          "videoType": "VOD",
          "genre": "General"
        },
        {
          "videoId": "n_KcExOCZPU",
          "title": "बिलासपुर में बारिश के कारण धंस गई सड़क, बना विशाल गड्ढा, हाdसे का खतरा बढ़ा | CG Bhaskar",
          "description": "बिलासपुर में लगातार हो रही मूसलाधार बारिश अब सड़कों की हकीकत भी ...",
          "channelTitle": "CG Bhaskar",
          "publishedAt": "2026-07-18T14:45:05Z",
          "thumbnail": "https://i.ytimg.com/vi/n_KcExOCZPU/hqdefault.jpg",
          "durationSeconds": 178,
          "durationFormatted": "02:58",
          "views": 560,
          "likes": 12,
          "videoType": "VOD",
          "genre": "General"
        },
        {
          "videoId": "vlrC2z7dN_M",
          "title": "Shefali Bagga के घर से मिले 30 लाख कैश! पूछताछ में दिया बड़ा बयान #shefalibagga #MahadevCase",
          "description": "जांच में शेफाली बग्गा के घर से मिले 30 लाख कैश! पूछताछ में दिया बड़ा ...",
          "channelTitle": "Vayam Chhattisgarh",
          "publishedAt": "2026-07-18T14:32:33Z",
          "thumbnail": "https://i.ytimg.com/vi/vlrC2z7dN_M/hqdefault.jpg",
          "durationSeconds": 57,
          "durationFormatted": "00:57",
          "views": 707,
          "likes": 2,
          "videoType": "VOD",
          "genre": "General"
        }
      ],
      "sectionIndex": 1
    },
    {
      "section": "Podcast",
      "count": 0,
      "items": [],
      "sectionIndex": 2
    },
    {
      "section": "Jobs",
      "count": 3,
      "items": [
        {
          "videoId": "CnqGFugW4pM",
          "title": "SI भर्ती की कठिन परीक्षा को लेकर क्या बोले डिप्टी सीएम विजय बघेल...?",
          "description": "SI भर्ती की कठिन परीक्षा को लेकर क्या बोले डिप्टी सीएम विजय बघेल...? Join ...",
          "channelTitle": "Bhilai Times",
          "publishedAt": "2026-07-19T13:00:13Z",
          "thumbnail": "https://i.ytimg.com/vi/CnqGFugW4pM/hqdefault.jpg",
          "durationSeconds": 63,
          "durationFormatted": "01:03",
          "views": 667,
          "likes": 16,
          "videoType": "VOD",
          "genre": "Jobs"
        },
        {
          "videoId": "JAhpq67cb3A",
          "title": "भीषण सड़क हाdसे की चपेट में शर्मा परिवार, डोंगरगढ़ से हो रही थी वापसी। 9 भर्ती 1 की मौt। Yogesh।",
          "description": "भीषण सड़क हाdसे की चपेट में शर्मा परिवार, डोंगरगढ़ से हो रही थी वापसी ...",
          "channelTitle": "Bhilai Times",
          "publishedAt": "2026-07-18T18:00:07Z",
          "thumbnail": "https://i.ytimg.com/vi/JAhpq67cb3A/hqdefault.jpg",
          "durationSeconds": 524,
          "durationFormatted": "08:44",
          "views": 5130,
          "likes": 65,
          "videoType": "VOD",
          "genre": "Jobs"
        },
        {
          "videoId": "9cO8OQC0KXU",
          "title": "बिलासपुर में कांग्रेस का प्रदर्शन, करंट लगने से मौt पर 1 करोड़ मुआवजा और सरकारी नौकरी की रखी मांग |",
          "description": "बिलासपुर में कांग्रेस का प्रदर्शन, करंट लगने से मौt पर 1 करोड़ मुआवडा ...",
          "channelTitle": "CG Bhaskar",
          "publishedAt": "2026-07-18T15:15:09Z",
          "thumbnail": "https://i.ytimg.com/vi/9cO8OQC0KXU/hqdefault.jpg",
          "durationSeconds": 282,
          "durationFormatted": "04:42",
          "views": 233,
          "likes": 12,
          "videoType": "VOD",
          "genre": "Jobs"
        }
      ],
      "sectionIndex": 3
    },
    {
      "section": "Politics",
      "count": 14,
      "items": [
        {
          "videoId": "nrgk_Xa7mI4",
          "title": "Raipur Youth Protest: Sonam Wangchuk के समर्थन में युवाओं का प्रदर्शन,केंद्र सरकार के खिलाफ नारेबाजी",
          "description": "IBC24, Raipur Youth Protest: Sonam Wangchuk के समर्थन में युवाओं का प्रदर्शन,केंद्र ...",
          "channelTitle": "IBC24",
          "publishedAt": "2026-07-19T12:53:46Z",
          "thumbnail": "https://i.ytimg.com/vi/nrgk_Xa7mI4/hqdefault.jpg",
          "durationSeconds": 104,
          "durationFormatted": "01:44",
          "views": 311,
          "likes": 0,
          "videoType": "VOD",
          "genre": "Politics"
        },
        {
          "videoId": "otCIt3tfIow",
          "title": "MP News : CM मोहन यादव ने UCC पर कही बड़ी बात, हर नागरिक को मिलेगा समान अधिकार और समान न्याय |",
          "description": "मध्य प्रदेश कैबिनेट ने समान नागरिक संहिता (UCC) विधेयक 2026 को मंजूरी ...",
          "channelTitle": "India News Madhya Pradesh Chhattisgarh",
          "publishedAt": "2026-07-19T12:51:59Z",
          "thumbnail": "https://i.ytimg.com/vi/otCIt3tfIow/hqdefault.jpg",
          "durationSeconds": 406,
          "durationFormatted": "06:46",
          "views": 7,
          "likes": 0,
          "videoType": "VOD",
          "genre": "Politics"
        },
        {
          "videoId": "RTPh1CxYbic",
          "title": "MP News : CM मोहन यादव की कैबिनेट बैठक पर मंत्रियों का बड़ा बयान, EXCLUSIVE रिपोर्ट |",
          "description": "CM मोहन यादव की जगदीशपुर में हुई कैबिनेट बैठक को लेकर मंत्रियों से ...",
          "channelTitle": "India News Madhya Pradesh Chhattisgarh",
          "publishedAt": "2026-07-19T11:07:16Z",
          "thumbnail": "https://i.ytimg.com/vi/RTPh1CxYbic/hqdefault.jpg",
          "durationSeconds": 445,
          "durationFormatted": "07:25",
          "views": 73,
          "likes": 1,
          "videoType": "VOD",
          "genre": "Politics"
        },
        {
          "videoId": "tpSWgrezAeM",
          "title": "नकटी त्रासदी पर बरसे चंद्रपुर विधायक रामकुमार यादव दागे तीखे सवाल...",
          "description": "नकटी त्रासदी पर बरसे चंद्रपुर विधायक रामकुमार यादव दागे तीखे सवाल.",
          "channelTitle": "Bhilai Times",
          "publishedAt": "2026-07-19T11:00:33Z",
          "thumbnail": "https://i.ytimg.com/vi/tpSWgrezAeM/hqdefault.jpg",
          "durationSeconds": 93,
          "durationFormatted": "01:33",
          "views": 2496,
          "likes": 113,
          "videoType": "VOD",
          "genre": "Politics"
        },
        {
          "videoId": "gvask8gcN9I",
          "title": "MP News : CM मोहन यादव ने बदला इतिहास! 308 साल बाद लौटी जगदीशपुर की पुरानी पहचान |",
          "description": "मध्य प्रदेश के जगदीशपुर में हुई मोहन कैबिनेट की बैठक के दौरान एक बार ...",
          "channelTitle": "India News Madhya Pradesh Chhattisgarh",
          "publishedAt": "2026-07-19T10:46:04Z",
          "thumbnail": "https://i.ytimg.com/vi/gvask8gcN9I/hqdefault.jpg",
          "durationSeconds": 316,
          "durationFormatted": "05:16",
          "views": 10,
          "likes": 1,
          "videoType": "VOD",
          "genre": "Politics"
        },
        {
          "videoId": "O-9BXZwIjB8",
          "title": "MP News : CM मोहन यादव का बड़ा बयान , 3.49 करोड़ SMS के बाद MP में UCC को मिली मंजूरी |",
          "description": "मध्य प्रदेश की मोहन कैबिनेट ने समान नागरिक संहिता (UCC) के प्रस्ताव ...",
          "channelTitle": "India News Madhya Pradesh Chhattisgarh",
          "publishedAt": "2026-07-19T10:20:13Z",
          "thumbnail": "https://i.ytimg.com/vi/O-9BXZwIjB8/hqdefault.jpg",
          "durationSeconds": 342,
          "durationFormatted": "05:42",
          "views": 11,
          "likes": 0,
          "videoType": "VOD",
          "genre": "Politics"
        },
        {
          "videoId": "_jd688gobe8",
          "title": "MP News: VVIP सुरक्षा में चूक! Tikamgarh SP पर गिरी गाज.. CM यादव के निर्देश पर बड़ा एक्शन",
          "description": "IBC24, MP News: VVIP सुरक्षा में चूक! Tikamgarh SP पर गिरी गाज.. CM यादव के निर्देश ...",
          "channelTitle": "IBC24",
          "publishedAt": "2026-07-19T10:09:41Z",
          "thumbnail": "https://i.ytimg.com/vi/_jd688gobe8/hqdefault.jpg",
          "durationSeconds": 109,
          "durationFormatted": "01:49",
          "views": 120,
          "likes": 0,
          "videoType": "VOD",
          "genre": "Politics"
        },
        {
          "videoId": "dDfWCzmwU7k",
          "title": "Bilaspur में 3 बड़ी घटनाएं, नेता को सुपारी देकर Marवाने की कोशिश। जानें सारी घटनाएं इसी रिपोर्ट में",
          "description": "Bilaspur में 3 बड़ी घटनाएं, नेता को सुपारी देकर Marवाने की कोशिश। जानें ...",
          "channelTitle": "CG Bhaskar",
          "publishedAt": "2026-07-19T09:54:52Z",
          "thumbnail": "https://i.ytimg.com/vi/dDfWCzmwU7k/hqdefault.jpg",
          "durationSeconds": 323,
          "durationFormatted": "05:23",
          "views": 292,
          "likes": 6,
          "videoType": "VOD",
          "genre": "Politics"
        },
        {
          "videoId": "d6o_mAWXVzg",
          "title": "Breaking News  : जगदीशपुर से CM मोहन यादव का बड़ा ऐलान, MP में UCC हुआ लागू  |",
          "description": "मध्य प्रदेश के मुख्यमंत्री डॉ. मोहन यादव की अध्यक्षता में जगदीशपुर ...",
          "channelTitle": "India News Madhya Pradesh Chhattisgarh",
          "publishedAt": "2026-07-19T09:39:06Z",
          "thumbnail": "https://i.ytimg.com/vi/d6o_mAWXVzg/hqdefault.jpg",
          "durationSeconds": 1675,
          "durationFormatted": "27:55",
          "views": 30,
          "likes": 0,
          "videoType": "VOD",
          "genre": "Politics"
        },
        {
          "videoId": "ReZJVNEVYwU",
          "title": "Ram Mandir Chanda Chori Case: चढ़ावा चोरी पर सियासी संग्राम। Rahul-Kharge ने PM Modi को लिखा पत्र",
          "description": "IBC24, Ram Mandir Chanda Chori Case: चढ़ावा चोरी पर सियासी संग्राम। Rahul-Kharge ने PM ...",
          "channelTitle": "IBC24",
          "publishedAt": "2026-07-19T08:55:41Z",
          "thumbnail": "https://i.ytimg.com/vi/ReZJVNEVYwU/hqdefault.jpg",
          "durationSeconds": 283,
          "durationFormatted": "04:43",
          "views": 1110,
          "likes": 0,
          "videoType": "VOD",
          "genre": "Politics"
        },
        {
          "videoId": "eOLogwoQJCA",
          "title": "Ayodhya Viral Video: सरयू नदी में मटन और पीयर पार्टी पर एक्शन। पुलिस ने 3 आरोपियों को किया गिरफ्तार",
          "description": "IBC24, Ayodhya Viral Video: सरयू नदी में मटन और पीयर पार्टी पर एक्शन। पुलिस ने 3 ...",
          "channelTitle": "IBC24",
          "publishedAt": "2026-07-19T08:31:11Z",
          "thumbnail": "https://i.ytimg.com/vi/eOLogwoQJCA/hqdefault.jpg",
          "durationSeconds": 122,
          "durationFormatted": "02:02",
          "views": 180,
          "likes": 0,
          "videoType": "VOD",
          "genre": "Politics"
        },
        {
          "videoId": "znemxPVC524",
          "title": "Datiya Byelection 2026 : BJP-कांग्रेस का बड़ा दांव, जातीय समीकरण तय करेंगे जीत-हार |",
          "description": "दतिया विधानसभा उपचुनाव में चुनाव प्रचार अब निर्णायक दौर में पहुंच ...",
          "channelTitle": "India News Madhya Pradesh Chhattisgarh",
          "publishedAt": "2026-07-19T08:28:37Z",
          "thumbnail": "https://i.ytimg.com/vi/znemxPVC524/hqdefault.jpg",
          "durationSeconds": 319,
          "durationFormatted": "05:19",
          "views": 55,
          "likes": 0,
          "videoType": "VOD",
          "genre": "Politics"
        },
        {
          "videoId": "-RfRIOYmYcM",
          "title": "CM Mohan Yadav : आज जगदीशपुर में बड़ी कैबिनेट बैठक, लिव-इन रिलेशनशिप पर हो सकता है बड़ा फैसला |",
          "description": "मध्य प्रदेश में मुख्यमंत्री डॉ. मोहन यादव की कैबिनेट बैठक में ...",
          "channelTitle": "India News Madhya Pradesh Chhattisgarh",
          "publishedAt": "2026-07-19T08:13:29Z",
          "thumbnail": "https://i.ytimg.com/vi/-RfRIOYmYcM/hqdefault.jpg",
          "durationSeconds": 244,
          "durationFormatted": "04:04",
          "views": 26,
          "likes": 0,
          "videoType": "VOD",
          "genre": "Politics"
        },
        {
          "videoId": "wbHGa-fyapw",
          "title": "CM Mohan Yadav : आज जगदीशपुर में लेंगे बड़ा फैसला, UCC को मिल सकती है मंजूरी | India News MP |",
          "description": "मध्य प्रदेश की मोहन यादव सरकार की आज जगदीशपुर में अहम कैबिनेट बैठक ...",
          "channelTitle": "India News Madhya Pradesh Chhattisgarh",
          "publishedAt": "2026-07-19T06:55:19Z",
          "thumbnail": "https://i.ytimg.com/vi/wbHGa-fyapw/hqdefault.jpg",
          "durationSeconds": 380,
          "durationFormatted": "06:20",
          "views": 14,
          "likes": 0,
          "videoType": "VOD",
          "genre": "Politics"
        }
      ],
      "sectionIndex": 4
    },
    {
      "section": "Events",
      "count": 2,
      "items": [
        {
          "videoId": "CnUf-8u0f8M",
          "title": "🔴IBC24 पर कीजिए सालासर बालाजी धाम के Live दर्शन । Shree Salasar Balaji Dham Mandir से Aarti Live",
          "description": "IBC24, IBC24 पर कीजिए सालासर बालाजी धाम के Live दर्शन , Shree Salasar Balaji Dham Mandir से ...",
          "channelTitle": "IBC24",
          "publishedAt": "2026-07-19T13:02:25Z",
          "thumbnail": "https://i.ytimg.com/vi/CnUf-8u0f8M/hqdefault.jpg",
          "durationSeconds": 646,
          "durationFormatted": "10:46",
          "views": 54,
          "likes": 0,
          "videoType": "VOD",
          "genre": "Events"
        },
        {
          "videoId": "_Hc4x76axx0",
          "title": "रील बनाइए और पैसे कमाइए!धमतरी में स्पर्धा का आयोजन | CG Bhaskar",
          "description": "धमतरी के जिला प्रशासन द्वारा एक प्रतियोगिता आयोजित किया गया है ...",
          "channelTitle": "CG Bhaskar",
          "publishedAt": "2026-07-19T08:13:03Z",
          "thumbnail": "https://i.ytimg.com/vi/_Hc4x76axx0/hqdefault.jpg",
          "durationSeconds": 75,
          "durationFormatted": "01:15",
          "views": 223,
          "likes": 12,
          "videoType": "VOD",
          "genre": "Events"
        }
      ],
      "sectionIndex": 5
    },
    {
      "section": "Civic",
      "count": 2,
      "items": [
        {
          "videoId": "I5b9NYWQYSE",
          "title": "घटिया हालत में नेहरू नगर Underbridge जिम्मेदार कौन? | CG Bhaskar",
          "description": "घटिया हालत में नेहरू नगर Underbridge जिम्मेदार कौन? Join our Whatsapp Group ...",
          "channelTitle": "CG Bhaskar",
          "publishedAt": "2026-07-19T13:30:36Z",
          "thumbnail": "https://i.ytimg.com/vi/I5b9NYWQYSE/hqdefault.jpg",
          "durationSeconds": 95,
          "durationFormatted": "01:35",
          "views": 22,
          "likes": 3,
          "videoType": "VOD",
          "genre": "Civic"
        },
        {
          "videoId": "5PCchZSH4x8",
          "title": "नगर निगम की लापरवाही, दुकानों में घुसा पानी | CG Bhaskar",
          "description": "नगर निगम की लापरवाही, दुकानों में घुसा पानी | CG Bhaskar छत्तीसगढ़ की ...",
          "channelTitle": "CG Bhaskar",
          "publishedAt": "2026-07-19T11:28:39Z",
          "thumbnail": "https://i.ytimg.com/vi/5PCchZSH4x8/hqdefault.jpg",
          "durationSeconds": 116,
          "durationFormatted": "01:56",
          "views": 175,
          "likes": 7,
          "videoType": "VOD",
          "genre": "Civic"
        }
      ],
      "sectionIndex": 6
    },
    {
      "section": "Traffic",
      "count": 0,
      "items": [],
      "sectionIndex": 7
    },
    {
      "section": "Crime",
      "count": 6,
      "items": [
        {
          "videoId": "W3Np4lT-TSQ",
          "title": "Bhilai का शीतला तालाब बदहाल! नशाखोरी रोकी तो कर दी मारपीट!",
          "description": "news #bhilainews #kpnewsbhilai #kpnewscg #kpnews #cgnews #chhattisgarh #chhattisgarhnews #bhilai #bhilaidurg ...",
          "channelTitle": "KPNews",
          "publishedAt": "2026-07-19T13:01:53Z",
          "thumbnail": "https://i.ytimg.com/vi/W3Np4lT-TSQ/hqdefault.jpg",
          "durationSeconds": 122,
          "durationFormatted": "02:02",
          "views": 60,
          "likes": 0,
          "videoType": "VOD",
          "genre": "Crime"
        },
        {
          "videoId": "7jwCq_lRn-U",
          "title": "राम मंदिर चंदा चोरी विवाद पर बरसे चंद्रपुर विधायक रामकुमार यादव...",
          "description": "राम मंदिर चंदा चोरी विवाद पर बरसे चंद्रपुर विधायक रामकुमार यादव.",
          "channelTitle": "Bhilai Times",
          "publishedAt": "2026-07-19T12:00:25Z",
          "thumbnail": "https://i.ytimg.com/vi/7jwCq_lRn-U/hqdefault.jpg",
          "durationSeconds": 130,
          "durationFormatted": "02:10",
          "views": 1944,
          "likes": 80,
          "videoType": "VOD",
          "genre": "Crime"
        },
        {
          "videoId": "BGUf3MMrxDk",
          "title": "Jammu Kashmir Cloudburst: पुंछ-किश्तवाड़ में फटे बादल। फ्लैश-फ्लड में 10 लोगों की मौत। देखिए..",
          "description": "IBC24, Jammu Kashmir Cloudburst: पुंछ-किश्तवाड़ में फटे बादल। फ्लैश-फ्लड में 10 ...",
          "channelTitle": "IBC24",
          "publishedAt": "2026-07-19T09:27:01Z",
          "thumbnail": "https://i.ytimg.com/vi/BGUf3MMrxDk/hqdefault.jpg",
          "durationSeconds": 63,
          "durationFormatted": "01:03",
          "views": 112,
          "likes": 0,
          "videoType": "VOD",
          "genre": "Crime"
        },
        {
          "videoId": "5W596XQpcxI",
          "title": "कानून व्यवस्था और ओपन जेल प्रणाली पर क्या बोले डिप्टी सीएम विजय शर्मा?",
          "description": "कानून व्यवस्था और ओपन जेल प्रणाली पर क्या बोले डिप्टी सीएम विजय ...",
          "channelTitle": "Bhilai Times",
          "publishedAt": "2026-07-19T08:00:12Z",
          "thumbnail": "https://i.ytimg.com/vi/5W596XQpcxI/hqdefault.jpg",
          "durationSeconds": 99,
          "durationFormatted": "01:39",
          "views": 4318,
          "likes": 119,
          "videoType": "VOD",
          "genre": "Crime"
        },
        {
          "videoId": "-IKusMz433o",
          "title": "Ram Mandir Donation Case: राम मंदिर दान विवाद पर सियासत तेज! Rahul Gandhi ने PM Modi को लिखा पत्र",
          "description": "IBC24, Ram Mandir Donation Case: राम मंदिर दान विवाद पर सियासत तेज! Rahul Gandhi ने PM Modi ...",
          "channelTitle": "IBC24",
          "publishedAt": "2026-07-19T07:57:56Z",
          "thumbnail": "https://i.ytimg.com/vi/-IKusMz433o/hqdefault.jpg",
          "durationSeconds": 92,
          "durationFormatted": "01:32",
          "views": 157,
          "likes": 0,
          "videoType": "VOD",
          "genre": "Crime"
        },
        {
          "videoId": "EklBm65OFyg",
          "title": "Bhilai: युवक पर चा.कू से हमला, चश्मदीद और परिजनों ने कही ये बात || KP NEWS || Faizan",
          "description": "news #bhilainews #kpnewsbhilai #kpnewscg #kpnews #cgnews #chhattisgarh #chhattisgarhnews #bhilai #bhilaidurg ...",
          "channelTitle": "KPNews",
          "publishedAt": "2026-07-18T15:30:01Z",
          "thumbnail": "https://i.ytimg.com/vi/EklBm65OFyg/hqdefault.jpg",
          "durationSeconds": 644,
          "durationFormatted": "10:44",
          "views": 3977,
          "likes": 0,
          "videoType": "VOD",
          "genre": "Crime"
        }
      ],
      "sectionIndex": 8
    }
  ]
}