{
  "generatedAt": "2026-06-04T17:27:16.125609Z",
  "clusterCount": 5,
  "clusters": [
    {
      "clusterId": "public-sector-exam",
      "topic": "Public Sector Exam",
      "videoCount": 21,
      "trendScore": 58.5,
      "topVideos": [
        {
          "index": 1,
          "videoId": "VVVpV4lKWFQ",
          "title": "असिस्टेंट प्रोफेसर की 7 साल से नहीं हुई भर्ती| अभ्यर्थी परेशान| झूठ बोल रहे मंत्री| Yashwant |",
          "description": "असिस्टेंट प्रोफेसर की 7 साल से नहीं हुई भर्ती| अभ्यर्थी परेशान| झूठ ...",
          "channelTitle": "Bhilai Times",
          "publishedAt": "2026-06-04T02:00:35Z",
          "thumbnail": "https://i.ytimg.com/vi/VVVpV4lKWFQ/hqdefault.jpg",
          "durationSeconds": 822,
          "durationFormatted": "13:42",
          "views": 8299,
          "likes": 360,
          "videoType": "VOD",
          "genre": "Jobs"
        },
        {
          "index": 2,
          "videoId": "sT3b-U3KwvQ",
          "title": "D.El.Ed Exam में बवाल | St. Thomas College की गलती? | Checking से Students हुए वांछित",
          "description": "D.El.Ed Exam में बवाल | St. Thomas College की गलती? | Checking से Students हुए वांछित Report/Story: ...",
          "channelTitle": "Bhilai Times",
          "publishedAt": "2026-06-04T12:30:26Z",
          "thumbnail": "https://i.ytimg.com/vi/sT3b-U3KwvQ/hqdefault.jpg",
          "durationSeconds": 541,
          "durationFormatted": "09:01",
          "views": 6625,
          "likes": 241,
          "videoType": "VOD",
          "genre": "General"
        },
        {
          "index": 3,
          "videoId": "oYvoRy-OHcc",
          "title": "अल्टीमेटम के साथ टली नायब तहसीलदारों की हड़ताल | MLA-नायब तहसीलदार विवाद में बड़ा अपडेट |@tirandaj",
          "description": "MLA-NaibTehsildarDispute #MLA-NaibTehsildarDisputeUpdate #RamkumarToppo #TusharManik ...",
          "channelTitle": "Tirandaj",
          "publishedAt": "2026-06-04T04:00:35Z",
          "thumbnail": "https://i.ytimg.com/vi/oYvoRy-OHcc/hqdefault.jpg",
          "durationSeconds": 568,
          "durationFormatted": "09:28",
          "views": 5159,
          "likes": 47,
          "videoType": "VOD",
          "genre": "Crime"
        },
        {
          "index": 4,
          "videoId": "dYyA0yEDP2A",
          "title": "4 June 2026 CG News Today | Chhattisgarh Breaking News | CG Fatafat News | Raipur News | CM Vishnu ",
          "description": "4 June 2026 CG News Today | Chhattisgarh Breaking News | CG Fatafat News | Raipur News | CM Vishnu #ChhattisgarhNews ...",
          "channelTitle": "Suprabhat News  Chhattisgarh",
          "publishedAt": "2026-06-03T23:31:23Z",
          "thumbnail": "https://i.ytimg.com/vi/dYyA0yEDP2A/hqdefault.jpg",
          "durationSeconds": 857,
          "durationFormatted": "14:17",
          "views": 5003,
          "likes": 86,
          "videoType": "VOD",
          "genre": "Politics"
        },
        {
          "index": 5,
          "videoId": "nRHYFfbwsxo",
          "title": "इसी नाम से नहीं पहुंच रहा आपके गांव-घर तक पानी",
          "description": "jaljeevanmission #chhattisgarhsamachar #narendramodi #pmmodi #corruptionpakistan #WaterSchem #ChhattisgarhNews ...",
          "channelTitle": "CG BOX",
          "publishedAt": "2026-06-04T10:06:31Z",
          "thumbnail": "https://i.ytimg.com/vi/nRHYFfbwsxo/hqdefault.jpg",
          "durationSeconds": 73,
          "durationFormatted": "01:13",
          "views": 4454,
          "likes": 313,
          "videoType": "VOD",
          "genre": "General"
        }
      ],
      "latestUpdateAt": "2026-06-04T16:21:50Z"
    },
    {
      "clusterId": "location-raipur",
      "topic": "Raipur",
      "videoCount": 10,
      "trendScore": 47.7,
      "topVideos": [
        {
          "index": 1,
          "videoId": "8SSKwOACthc",
          "title": "रायपुर में घर बनाना हुआ महंगा",
          "description": "latestnews #raipur #chhattisgarhsamachar #breakingnews #raipur.",
          "channelTitle": "Thiha Chhattisgarh",
          "publishedAt": "2026-06-04T15:30:25Z",
          "thumbnail": "https://i.ytimg.com/vi/8SSKwOACthc/hqdefault.jpg",
          "durationSeconds": 155,
          "durationFormatted": "02:35",
          "views": 6202,
          "likes": 198,
          "videoType": "VOD",
          "genre": "General"
        },
        {
          "index": 2,
          "videoId": "x93kFZkgUrU",
          "title": "Thiha CG Special: बस का धंधा करने वाले का धमाकेदार Interview | रायपुर के पूर्व महापौर प्रमोद दुबे",
          "description": "Thiha CG Special: बस का धंधा करने वाले का धमाकेदार Interview | रायपुर के पूर्व ...",
          "channelTitle": "Thiha Chhattisgarh",
          "publishedAt": "2026-06-04T15:00:14Z",
          "thumbnail": "https://i.ytimg.com/vi/x93kFZkgUrU/hqdefault.jpg",
          "durationSeconds": 4449,
          "durationFormatted": "01:14:09",
          "views": 3362,
          "likes": 184,
          "videoType": "VOD",
          "genre": "General"
        },
        {
          "index": 3,
          "videoId": "CYWPGk72WHI",
          "title": "Chhattisgarh Panchayat Politics Interview Swati Verma BJP जिला पंचायत सभापति रायपुर | Neta By Choice",
          "description": "swativerma #netabychoice #bjp #chhattisgarhpolitics #chhattisgarhnews #cgpolitics #raipurnews #swativerma #bjpchhattisgarh ...",
          "channelTitle": "CG BOX",
          "publishedAt": "2026-06-04T13:53:18Z",
          "thumbnail": "https://i.ytimg.com/vi/CYWPGk72WHI/hqdefault.jpg",
          "durationSeconds": 2968,
          "durationFormatted": "49:28",
          "views": 634,
          "likes": 51,
          "videoType": "VOD",
          "genre": "Politics"
        },
        {
          "index": 4,
          "videoId": "hFgjy4aznT0",
          "title": "04 जून 2026 | छत्तीसगढ़ का ताजा खबर| CG News | Raipur News Today | Chattisgarh News Hindi",
          "description": "04 जून 2026 | छत्तीसगढ़ का ताजा खबर| CG News | Raipur News Today | Chattisgarh News Hindi ...",
          "channelTitle": "Chhattisgarh ka awaaz 07 ",
          "publishedAt": "2026-06-03T23:30:03Z",
          "thumbnail": "https://i.ytimg.com/vi/hFgjy4aznT0/hqdefault.jpg",
          "durationSeconds": 942,
          "durationFormatted": "15:42",
          "views": 512,
          "likes": 3,
          "videoType": "VOD",
          "genre": "General"
        },
        {
          "index": 5,
          "videoId": "dtXUtuPnXaA",
          "title": "04 जून, 2026 | प्रादेशिक हिन्दी समाचार/आकाशवाणी रायपुर/Chhattisgarh Newsonair",
          "description": "",
          "channelTitle": "CHHATTISGARH AIR NEWS",
          "publishedAt": "2026-06-04T14:47:59Z",
          "thumbnail": "https://i.ytimg.com/vi/dtXUtuPnXaA/hqdefault.jpg",
          "durationSeconds": 645,
          "durationFormatted": "10:45",
          "views": 303,
          "likes": 18,
          "videoType": "VOD",
          "genre": "General"
        }
      ],
      "latestUpdateAt": "2026-06-04T15:30:25Z"
    },
    {
      "clusterId": "location-durg",
      "topic": "Durg",
      "videoCount": 6,
      "trendScore": 39.3,
      "topVideos": [
        {
          "index": 1,
          "videoId": "IRdKT3VJPDM",
          "title": "Chhattisgarh में Ebola Virus की एंट्री, Durg में 3 संदिग्ध मिलने से हड़कंप #EbolaVirus #Durg #cgnews",
          "description": "छत्तीसगढ़ में 'इबोला' वायरस की एंट्री, दुर्ग में 3 संदिग्ध मिलने से ...",
          "channelTitle": "Vayam Chhattisgarh",
          "publishedAt": "2026-06-04T08:34:22Z",
          "thumbnail": "https://i.ytimg.com/vi/IRdKT3VJPDM/hqdefault.jpg",
          "durationSeconds": 70,
          "durationFormatted": "01:10",
          "views": 776,
          "likes": 10,
          "videoType": "VOD",
          "genre": "General"
        },
        {
          "index": 2,
          "videoId": "UtImSQMmKDc",
          "title": "करोड़ों की अफीम हुई राख, दुर्ग पुलिस की बड़ी कार्रवाई | CG Bhaskar",
          "description": "करोड़ों की अफीम हुई राख, दुर्ग पुलिस की बड़ी कार्रवाई | CG Bhaskar दुर्ग ...",
          "channelTitle": "CG Bhaskar",
          "publishedAt": "2026-06-04T12:56:15Z",
          "thumbnail": "https://i.ytimg.com/vi/UtImSQMmKDc/hqdefault.jpg",
          "durationSeconds": 61,
          "durationFormatted": "01:01",
          "views": 441,
          "likes": 13,
          "videoType": "VOD",
          "genre": "General"
        },
        {
          "index": 3,
          "videoId": "wWfip97Xxyg",
          "title": "दुर्ग जिले में इबोला वायरस की दस्तक? | CG Bhaskar",
          "description": "दुर्ग जिले में इबोला वायरस की दस्तक? | CG Bhaskar Join our Whatsapp Group ...",
          "channelTitle": "CG Bhaskar",
          "publishedAt": "2026-06-04T11:45:28Z",
          "thumbnail": "https://i.ytimg.com/vi/wWfip97Xxyg/hqdefault.jpg",
          "durationSeconds": 179,
          "durationFormatted": "02:59",
          "views": 380,
          "likes": 12,
          "videoType": "VOD",
          "genre": "General"
        },
        {
          "index": 4,
          "videoId": "jYJheitNIY0",
          "title": "दुर्ग में ईसाई धर्म अपनाए 175 हिंदुओं की घर वापसी, मंत्रोच्चार  से हुआ शुद्धिकरण | CG Bhaskar",
          "description": "दुर्ग में ईसाई धर्म अपनाए 175 हिंदुओं की घर वापसी, मंत्रोच्चार से हुआ ...",
          "channelTitle": "CG Bhaskar",
          "publishedAt": "2026-06-04T11:30:27Z",
          "thumbnail": "https://i.ytimg.com/vi/jYJheitNIY0/hqdefault.jpg",
          "durationSeconds": 875,
          "durationFormatted": "14:35",
          "views": 191,
          "likes": 44,
          "videoType": "VOD",
          "genre": "General"
        },
        {
          "index": 5,
          "videoId": "Sy6J81qSMPk",
          "title": "Durg News : दुर्ग में साइकिल रैली के जरिए फिटनेस का प्रचार",
          "description": "विश्व साइकिल दिवस के अवसर पर दुर्ग के घनश्याम सिंह आर्य कन्या ...",
          "channelTitle": "UNA MPCG",
          "publishedAt": "2026-06-04T06:40:40Z",
          "thumbnail": "https://i.ytimg.com/vi/Sy6J81qSMPk/hqdefault.jpg",
          "durationSeconds": 51,
          "durationFormatted": "00:51",
          "views": 81,
          "likes": 3,
          "videoType": "VOD",
          "genre": "Politics"
        }
      ],
      "latestUpdateAt": "2026-06-04T12:56:15Z"
    },
    {
      "clusterId": "location-bhilai",
      "topic": "Bhilai",
      "videoCount": 7,
      "trendScore": 36.9,
      "topVideos": [
        {
          "index": 1,
          "videoId": "eYg1FDw8Z4E",
          "title": "Bhilai में 30-35 लोगों ने घर में घुसकर, अकेली महिला से की अभद्रता! || KP NEWS || Janvi Sahu",
          "description": "news #bhilainews #kpnewsbhilai #kpnewscg #kpnews #cgnews #chhattisgarh #chhattisgarhnews #bhilai #bhilaidurg ...",
          "channelTitle": "KPNews",
          "publishedAt": "2026-06-04T11:03:31Z",
          "thumbnail": "https://i.ytimg.com/vi/eYg1FDw8Z4E/hqdefault.jpg",
          "durationSeconds": 929,
          "durationFormatted": "15:29",
          "views": 2594,
          "likes": 0,
          "videoType": "VOD",
          "genre": "General"
        },
        {
          "index": 2,
          "videoId": "H29UpPe_7QY",
          "title": "Bhilai मे सड़क पर उतरा मुस्लिम संगठन गौ माता के लिए कहा ये! || KP News || Faizan",
          "description": "news #bhilainews #kpnewsbhilai #kpnewscg #kpnews #cgnews #chhattisgarh #chhattisgarhnews #bhilai #bhilaidurg ...",
          "channelTitle": "KPNews",
          "publishedAt": "2026-06-04T14:02:13Z",
          "thumbnail": "https://i.ytimg.com/vi/H29UpPe_7QY/hqdefault.jpg",
          "durationSeconds": 528,
          "durationFormatted": "08:48",
          "views": 702,
          "likes": 0,
          "videoType": "VOD",
          "genre": "General"
        },
        {
          "index": 3,
          "videoId": "qoQDKu_HDic",
          "title": "चॉइस सेंटर में पैसा गमन। बड़ा फ्रॉ.ड बड़ा खुलासा। परेश!न ग़रीब। Aaj Bhilai। Sagar Sahu।",
          "description": "चॉइस सेंटर में पैसा गमन। बड़ा फ्रॉ.ड बड़ा खुलासा। परेश!न ग़रीब। Aaj Bhilai ...",
          "channelTitle": "Aaj Bhilai ",
          "publishedAt": "2026-06-04T13:24:33Z",
          "thumbnail": "https://i.ytimg.com/vi/qoQDKu_HDic/hqdefault.jpg",
          "durationSeconds": 955,
          "durationFormatted": "15:55",
          "views": 419,
          "likes": 46,
          "videoType": "VOD",
          "genre": "Crime"
        },
        {
          "index": 4,
          "videoId": "_iA_EPkd46o",
          "title": "Bhilai - 3 के दो Sub Inspector हुए लाइन अटैच | रिश्वत मांगते हुआ था Audio Viral | Khush | CG Bhaskar",
          "description": "Bhilai - 3 के दो Sub Inspector हुए लाइन अटैच | रिश्वत मांगते हुआ था Audio Viral | Khush | CG ...",
          "channelTitle": "CG Bhaskar",
          "publishedAt": "2026-06-04T09:30:34Z",
          "thumbnail": "https://i.ytimg.com/vi/_iA_EPkd46o/hqdefault.jpg",
          "durationSeconds": 974,
          "durationFormatted": "16:14",
          "views": 327,
          "likes": 7,
          "videoType": "VOD",
          "genre": "General"
        },
        {
          "index": 5,
          "videoId": "C4J7abg_r4s",
          "title": "महिला तस्कर को छोड़ने के लिए मांगी घूस, ऑडियो वायरल होते ही 2 SI सस्पेंड #durg  #bhilai #cgpolice",
          "description": "महिला तस्कर को छोड़ने के लिए मांगी घूस, ऑडियो वायरल होते ही 2 SI ...",
          "channelTitle": "Vayam Chhattisgarh",
          "publishedAt": "2026-06-04T11:56:27Z",
          "thumbnail": "https://i.ytimg.com/vi/C4J7abg_r4s/hqdefault.jpg",
          "durationSeconds": 79,
          "durationFormatted": "01:19",
          "views": 309,
          "likes": 9,
          "videoType": "VOD",
          "genre": "General"
        }
      ],
      "latestUpdateAt": "2026-06-04T15:59:44Z"
    },
    {
      "clusterId": "zee-mpcg",
      "topic": "Zee MPCG",
      "videoCount": 6,
      "trendScore": 31.2,
      "topVideos": [
        {
          "index": 1,
          "videoId": "DKCRecrDbYM",
          "title": "🔴LIVE : MP-CG News :  नगर पंचायत चुनाव में कौन भारी ? | Latest News | Zee MPCG",
          "description": "LIVE : MP-CG News : नगर पंचायत चुनाव में कौन भारी ? | Latest News | Zee MPCG सांसद ...",
          "channelTitle": "Zee Madhya Pradesh Chhattisgarh",
          "publishedAt": "2026-06-04T07:54:10Z",
          "thumbnail": "https://i.ytimg.com/vi/DKCRecrDbYM/hqdefault.jpg",
          "durationSeconds": 1626,
          "durationFormatted": "27:06",
          "views": 359,
          "likes": 5,
          "videoType": "VOD",
          "genre": "Politics"
        },
        {
          "index": 2,
          "videoId": "zMvDut2XNUE",
          "title": "🔴LIVE :  बरकतउल्ला विश्वविद्यालय पर सियासत  | Zee MPCG",
          "description": "LIVE : बरकतउल्ला विश्वविद्यालय पर सियासत | Zee MPCG #Live #amitshahinparliament ...",
          "channelTitle": "Zee Madhya Pradesh Chhattisgarh",
          "publishedAt": "2026-06-04T09:26:01Z",
          "thumbnail": "https://i.ytimg.com/vi/zMvDut2XNUE/hqdefault.jpg",
          "durationSeconds": 1547,
          "durationFormatted": "25:47",
          "views": 75,
          "likes": 1,
          "videoType": "VOD",
          "genre": "Politics"
        },
        {
          "index": 3,
          "videoId": "U_kP9Y0yXPU",
          "title": "🔴LIVE : MP-CG News : बरकतउल्ला विश्वविद्यालय का नाम बदलने पर सियासत | MP News | Zee MPCG",
          "description": "LIVE : MP-CG News : बरकतउल्ला विश्वविद्यालय का नाम बदलने पर सियासत | MP News ...",
          "channelTitle": "Zee Madhya Pradesh Chhattisgarh",
          "publishedAt": "2026-06-04T07:24:55Z",
          "thumbnail": "https://i.ytimg.com/vi/U_kP9Y0yXPU/hqdefault.jpg",
          "durationSeconds": 923,
          "durationFormatted": "15:23",
          "views": 56,
          "likes": 1,
          "videoType": "VOD",
          "genre": "Politics"
        },
        {
          "index": 4,
          "videoId": "fdU_fhQWaWQ",
          "title": "🔴LIVE : अधिकारियों पर क्यों बढ़ रही नाराजगी ? | Chhattisgarh News | CG News | Zee MPCG",
          "description": "LIVE : अधिकारियों पर क्यों बढ़ रही नाराजगी ? | Chhattisgarh News | CG News | Zee MPCG #Live ...",
          "channelTitle": "Zee Madhya Pradesh Chhattisgarh",
          "publishedAt": "2026-06-04T11:55:38Z",
          "thumbnail": "https://i.ytimg.com/vi/fdU_fhQWaWQ/hqdefault.jpg",
          "durationSeconds": 1622,
          "durationFormatted": "27:02",
          "views": 51,
          "likes": 1,
          "videoType": "VOD",
          "genre": "General"
        },
        {
          "index": 5,
          "videoId": "W05drHGNxII",
          "title": "🔴LIVE :  Aapki Aawaz : नशे में डॉक्टर..सवालों में सिस्टम ! | Zee MPCG | Latest News",
          "description": "LIVE : Aapki Aawaz : नशे में डॉक्टर..सवालों में सिस्टम ! | Zee MPCG | Latest News #Live ...",
          "channelTitle": "Zee Madhya Pradesh Chhattisgarh",
          "publishedAt": "2026-06-04T14:54:35Z",
          "thumbnail": "https://i.ytimg.com/vi/W05drHGNxII/hqdefault.jpg",
          "durationSeconds": 1381,
          "durationFormatted": "23:01",
          "views": 37,
          "likes": 0,
          "videoType": "VOD",
          "genre": "General"
        }
      ],
      "latestUpdateAt": "2026-06-04T14:54:35Z"
    }
  ]
}