{
  "generatedAt": "2026-02-02T08:00:44.865957Z",
  "clusterCount": 9,
  "clusters": [
    {
      "clusterId": "union-budget",
      "topic": "Union Budget",
      "videoCount": 17,
      "trendScore": 48.5,
      "topVideos": [
        {
          "index": 1,
          "videoId": "DXZ1cyvBR50",
          "title": "Union Budget 2026 :  बजट 2026 में बिहार को मिले सौगात पर क्या बोले CM नीतीश कुमार? | PM Modi |#bihar",
          "description": "Union Budget 2026 : बजट 2026 में बिहार को मिले सौगात पर क्या बोले CM नीतीश कुमार ...",
          "channelTitle": "News18 MP Chhattisgarh",
          "publishedAt": "2026-02-02T05:14:36Z",
          "thumbnail": "https://i.ytimg.com/vi/DXZ1cyvBR50/hqdefault.jpg",
          "durationSeconds": 234,
          "durationFormatted": "03:54",
          "views": 81461,
          "likes": 620,
          "videoType": "VOD",
          "genre": "Politics"
        },
        {
          "index": 2,
          "videoId": "N90ZMlfu6CI",
          "title": "Budget 2026: बजट में आम आदमी की बल्ले-बल्ले! ये 10 चीजे हो गई बहुत सस्ती | Nirmala Sitharaman",
          "description": "Budget 2026: बजट में आम आदमी की बल्ले-बल्ले! ये 10 चीजे हो गई बहुत सस्ती | Nirmala ...",
          "channelTitle": "News18 MP Chhattisgarh",
          "publishedAt": "2026-02-02T05:15:01Z",
          "thumbnail": "https://i.ytimg.com/vi/N90ZMlfu6CI/hqdefault.jpg",
          "durationSeconds": 185,
          "durationFormatted": "03:05",
          "views": 1052,
          "likes": 17,
          "videoType": "VOD",
          "genre": "Politics"
        },
        {
          "index": 3,
          "videoId": "AiB3VwGyj9U",
          "title": "Union Budget 2026: आम आदमी के लिए कितना फायदेमंद है इस बार का बजट, जीवन होगा आसान या मुश्किल ?",
          "description": "आज देश का आम बजट पेश हुआ है और अगले 4 मिनट में हम डिकोड करेंगे कि वित्त ...",
          "channelTitle": "Bansal News MPCG",
          "publishedAt": "2026-02-01T16:28:52Z",
          "thumbnail": "https://i.ytimg.com/vi/AiB3VwGyj9U/hqdefault.jpg",
          "durationSeconds": 149,
          "durationFormatted": "02:29",
          "views": 461,
          "likes": 7,
          "videoType": "VOD",
          "genre": "Politics"
        },
        {
          "index": 4,
          "videoId": "hUI2fm00LNk",
          "title": "Budget 2026 LIVE: वित्त मंत्री निर्मला सीतारमण LIVE | Union Budget News | FM Nirmala Sitharaman",
          "description": "Budget 2026 LIVE: वित्त मंत्री निर्मला सीतारमण LIVE | Union Budget News | FM Nirmala Sitharaman ...",
          "channelTitle": "NDTV MP Chhattisgarh",
          "publishedAt": "2026-02-01T20:57:28Z",
          "thumbnail": "https://i.ytimg.com/vi/hUI2fm00LNk/hqdefault.jpg",
          "durationSeconds": 11533,
          "durationFormatted": "03:12:13",
          "views": 415,
          "likes": 6,
          "videoType": "VOD",
          "genre": "Politics"
        },
        {
          "index": 5,
          "videoId": "Gj9ngaA6H_g",
          "title": "Railway Ticket Price: बजट के बाद और भी सस्ता हुआ रेल टिकट! | Budget 2026 | Breaking News | Top News",
          "description": "Railway Ticket Price: बजट के बाद और भी सस्ता हुआ रेल टिकट! | Budget 2026 | Breaking News | Top News ...",
          "channelTitle": "News18 MP Chhattisgarh",
          "publishedAt": "2026-02-02T04:12:07Z",
          "thumbnail": "https://i.ytimg.com/vi/Gj9ngaA6H_g/hqdefault.jpg",
          "durationSeconds": 184,
          "durationFormatted": "03:04",
          "views": 319,
          "likes": 4,
          "videoType": "VOD",
          "genre": "Politics"
        }
      ],
      "latestUpdateAt": "2026-02-02T06:31:21Z"
    },
    {
      "clusterId": "chhattisgarh-february",
      "topic": "Chhattisgarh February",
      "videoCount": 10,
      "trendScore": 41.2,
      "topVideos": [
        {
          "index": 1,
          "videoId": "8BFxroSpo9s",
          "title": "छत्तीसगढ़ आज की मुख्य समाचार | 2 फरवरी 2026 छत्तीसगढ़ की फटाफट ताजा खबरें | Chhattisgarh Samachar",
          "description": "छत्तीसगढ़ आज की मुख्य समाचार | 2 फरवरी 2026 छत्तीसगढ़ की फटाफट ताजा ...",
          "channelTitle": "छत्तीसगढ़ महतारी समाचार ",
          "publishedAt": "2026-02-01T23:30:04Z",
          "thumbnail": "https://i.ytimg.com/vi/8BFxroSpo9s/hqdefault.jpg",
          "durationSeconds": 1518,
          "durationFormatted": "25:18",
          "views": 15308,
          "likes": 238,
          "videoType": "VOD",
          "genre": "General"
        },
        {
          "index": 2,
          "videoId": "RWFGF7s0OSc",
          "title": "Chhattisgarh Samachar Today: CG News 2 February 2026 | CG Breaking News | Media CG",
          "description": "Chhattisgarh Samachar Today: CG News 2 February 2026 | CG Breaking News | Media CG News Instagram ...",
          "channelTitle": "Media Chhattisgarh",
          "publishedAt": "2026-02-01T23:46:24Z",
          "thumbnail": "https://i.ytimg.com/vi/RWFGF7s0OSc/hqdefault.jpg",
          "durationSeconds": 819,
          "durationFormatted": "13:39",
          "views": 13886,
          "likes": 244,
          "videoType": "VOD",
          "genre": "General"
        },
        {
          "index": 3,
          "videoId": "YrTmZKH6g1o",
          "title": "02 फरवरी 2026 | छत्तीसगढ़ का ताजा खबर| CG News | Raipur News Today | Chattisgarh News Hindi",
          "description": "02 फरवरी 2026 | छत्तीसगढ़ का ताजा खबर| CG News | Raipur News Today | Chattisgarh News Hindi ...",
          "channelTitle": "Chhattisgarh ka awaaz 07 ",
          "publishedAt": "2026-02-01T23:30:12Z",
          "thumbnail": "https://i.ytimg.com/vi/YrTmZKH6g1o/hqdefault.jpg",
          "durationSeconds": 959,
          "durationFormatted": "15:59",
          "views": 7005,
          "likes": 0,
          "videoType": "VOD",
          "genre": "General"
        },
        {
          "index": 4,
          "videoId": "H5nytHtiWYc",
          "title": "02 February 2026 | Chhattisgarh Ki 25 Khabre | CG News | Raipur News Today | Chattisgarh News Hindi",
          "description": "01 February 2026 | Chhattisgarh Ki 25 Khabre | CG News | Raipur News Today | Chattisgarh News Hindi दोस्तों आप ...",
          "channelTitle": "Chhattisgarh News Hindi ",
          "publishedAt": "2026-02-01T14:50:21Z",
          "thumbnail": "https://i.ytimg.com/vi/H5nytHtiWYc/hqdefault.jpg",
          "durationSeconds": 1129,
          "durationFormatted": "18:49",
          "views": 3919,
          "likes": 23,
          "videoType": "VOD",
          "genre": "General"
        },
        {
          "index": 5,
          "videoId": "hD4S-c7N-QY",
          "title": "2 February 2026 | छत्तीसगढ़ फटाफट खबरें Chhattisgarh Breaking News | Cg Samachar Today, Vishnu, Modi",
          "description": "2 February 2026 | छत्तीसगढ़ फटाफट खबरें Chhattisgarh Breaking News | Cg Samachar Today, Vishnu, Modi ...",
          "channelTitle": "Suprabhat News  Chhattisgarh",
          "publishedAt": "2026-02-01T23:33:33Z",
          "thumbnail": "https://i.ytimg.com/vi/hD4S-c7N-QY/hqdefault.jpg",
          "durationSeconds": 857,
          "durationFormatted": "14:17",
          "views": 3215,
          "likes": 91,
          "videoType": "VOD",
          "genre": "Politics"
        }
      ],
      "latestUpdateAt": "2026-02-02T00:30:06Z"
    },
    {
      "clusterId": "rajim-violence",
      "topic": "Rajim Violence",
      "videoCount": 11,
      "trendScore": 40.9,
      "topVideos": [
        {
          "index": 1,
          "videoId": "DajMPZj4yGs",
          "title": "Rajim Gariyaband Violence : राजिम में दो समुदायों में बवाल, धधक उठा पूरा गांव, भारी पुलिस बल तैनात",
          "description": "Rajim Violence News: राजिम: छत्तीसगढ़ के गरियाबंद ज़िले की धर्मनगरी राजिम के ...",
          "channelTitle": "IBC24",
          "publishedAt": "2026-02-02T02:06:52Z",
          "thumbnail": "https://i.ytimg.com/vi/DajMPZj4yGs/hqdefault_live.jpg",
          "durationSeconds": 0,
          "durationFormatted": "LIVE",
          "views": 5539,
          "likes": 0,
          "videoType": "LIVE",
          "genre": "Live"
        },
        {
          "index": 2,
          "videoId": "5nMoyGFS6j4",
          "title": "राजिम के दुतकैयां गांव में भारी बवाल #rajim #rajimnews #cgnews #chhattisgarh #gariyaband",
          "description": "IBC24, राजिम के दुतकैयां गांव में भारी बवाल #rajim #rajimnews #cgnews #chhattisgarh ...",
          "channelTitle": "IBC24",
          "publishedAt": "2026-02-02T07:33:09Z",
          "thumbnail": "https://i.ytimg.com/vi/5nMoyGFS6j4/hqdefault.jpg",
          "durationSeconds": 5,
          "durationFormatted": "00:05",
          "views": 2908,
          "likes": 0,
          "videoType": "VOD",
          "genre": "General"
        },
        {
          "index": 3,
          "videoId": "xB9vFFGpCdA",
          "title": "Rajim Violence: दुतकैयां गांव में 2 संप्रदाय के बीच हिंसक झड़प |घरों में आगजनी, गाड़ियों में लगाईं आग",
          "description": "IBC24, Rajim Violence: दुतकैयां गांव में 2 संप्रदाय के बीच हिंसक झड़प |घरों में ...",
          "channelTitle": "IBC24",
          "publishedAt": "2026-02-02T04:12:46Z",
          "thumbnail": "https://i.ytimg.com/vi/xB9vFFGpCdA/hqdefault.jpg",
          "durationSeconds": 596,
          "durationFormatted": "09:56",
          "views": 710,
          "likes": 0,
          "videoType": "VOD",
          "genre": "Crime"
        },
        {
          "index": 4,
          "videoId": "nVt9RQ0HWK8",
          "title": "Rajim  Violence Update : दुधकैया गांव में हिंसक झड़प | गांव म कर्फ्यू जइसे हालात..Police बल मौजूद",
          "description": "IBC24, Rajim Violence Update : दुधकैया गांव में हिंसक झड़प | गांव म कर्फ्यू जइसे ...",
          "channelTitle": "IBC24",
          "publishedAt": "2026-02-02T03:41:21Z",
          "thumbnail": "https://i.ytimg.com/vi/nVt9RQ0HWK8/hqdefault.jpg",
          "durationSeconds": 535,
          "durationFormatted": "08:55",
          "views": 472,
          "likes": 0,
          "videoType": "VOD",
          "genre": "Crime"
        },
        {
          "index": 5,
          "videoId": "YE7gVscAhO8",
          "title": "Rajim Violence: दुतकैयां गांव में विवाद से जुड़ा बड़ा अपडेट | ग्रामीणों ने किए चौंकाने वाले खुलासे",
          "description": "IBC24, Rajim Violence: राजिम के दुतकैयां गांव में विवाद से जुड़ा बड़ा अपडेट ...",
          "channelTitle": "IBC24",
          "publishedAt": "2026-02-02T05:35:01Z",
          "thumbnail": "https://i.ytimg.com/vi/YE7gVscAhO8/hqdefault.jpg",
          "durationSeconds": 826,
          "durationFormatted": "13:46",
          "views": 462,
          "likes": 0,
          "videoType": "VOD",
          "genre": "Crime"
        }
      ],
      "latestUpdateAt": "2026-02-02T07:52:41Z"
    },
    {
      "clusterId": "weather-rain",
      "topic": "Weather Rain",
      "videoCount": 6,
      "trendScore": 39.9,
      "topVideos": [
        {
          "index": 1,
          "videoId": "Cni4mRzaWDk",
          "title": "MP Weather: MP में 3 दिन मावठा का अलर्ट,इन जिलों में बारिश की चेतावनी,ओलावृष्टि से गेहूं फसल को खतरा",
          "description": "भोपाल: MP में तीन दिन मावठा का अलर्ट 25 जिलों में बारिश की चेतावनी ...",
          "channelTitle": "Bansal News MPCG",
          "publishedAt": "2026-02-02T03:09:15Z",
          "thumbnail": "https://i.ytimg.com/vi/Cni4mRzaWDk/hqdefault.jpg",
          "durationSeconds": 160,
          "durationFormatted": "02:40",
          "views": 5707,
          "likes": 118,
          "videoType": "VOD",
          "genre": "General"
        },
        {
          "index": 2,
          "videoId": "CVT48LcJyvY",
          "title": "MP Weather Update: Neemuch में खेतों में बिछ गई सफेद चादर, अफीम की फसल बर्बाद! Heavy Rain |Hailstorm",
          "description": "MP Weather Update: Neemuch में खेतों में बिछ गई सफेद चादर, अफीम की फसल बर्बाद!",
          "channelTitle": "NDTV MP Chhattisgarh",
          "publishedAt": "2026-02-02T02:25:31Z",
          "thumbnail": "https://i.ytimg.com/vi/CVT48LcJyvY/hqdefault.jpg",
          "durationSeconds": 346,
          "durationFormatted": "05:46",
          "views": 3179,
          "likes": 67,
          "videoType": "VOD",
          "genre": "General"
        },
        {
          "index": 3,
          "videoId": "ftZK5Vxj2xo",
          "title": "MP Weather Update: MP में 3 दिन गिरेगा मावठा..., 25 जिलों में अलर्ट, IMD की चेतावनी |Rain |Hailstorm",
          "description": "MP Weather Update: MP में 3 दिन गिरेगा मावठा..., 25 जिलों में अलर्ट, IMD की चेतावनी ...",
          "channelTitle": "NDTV MP Chhattisgarh",
          "publishedAt": "2026-02-02T01:58:11Z",
          "thumbnail": "https://i.ytimg.com/vi/ftZK5Vxj2xo/hqdefault.jpg",
          "durationSeconds": 748,
          "durationFormatted": "12:28",
          "views": 2732,
          "likes": 51,
          "videoType": "VOD",
          "genre": "General"
        },
        {
          "index": 4,
          "videoId": "tcfD9wj_Akw",
          "title": "MP Weather News: MP में ठंड के बीच 25 जिलों में बारिश का अलर्ट, किसानों की चिंता बढ़ी। IMD |Breaking",
          "description": "MP Weather News: MP में ठंड के बीच 25 जिलों में बारिश का अलर्ट, किसानों की ...",
          "channelTitle": "News18 MP Chhattisgarh",
          "publishedAt": "2026-02-02T03:53:25Z",
          "thumbnail": "https://i.ytimg.com/vi/tcfD9wj_Akw/hqdefault.jpg",
          "durationSeconds": 155,
          "durationFormatted": "02:35",
          "views": 1227,
          "likes": 6,
          "videoType": "VOD",
          "genre": "General"
        },
        {
          "index": 5,
          "videoId": "t6lShJsY8Ok",
          "title": "Hail fell in Neemuch: नीमच में ओलावृष्टि, फसलें तबाह, किसानों का दर्द, सरकार से मांग | MP Weather",
          "description": "Hail fell in Neemuch: नीमच में ओलावृष्टि, फसलें तबाह, किसानों का दर्द, सरकार से ...",
          "channelTitle": "NDTV MP Chhattisgarh",
          "publishedAt": "2026-02-02T07:05:21Z",
          "thumbnail": "https://i.ytimg.com/vi/t6lShJsY8Ok/hqdefault.jpg",
          "durationSeconds": 786,
          "durationFormatted": "13:06",
          "views": 208,
          "likes": 8,
          "videoType": "VOD",
          "genre": "General"
        }
      ],
      "latestUpdateAt": "2026-02-02T07:27:21Z"
    },
    {
      "clusterId": "silver-price",
      "topic": "Silver Price",
      "videoCount": 5,
      "trendScore": 39.3,
      "topVideos": [
        {
          "index": 1,
          "videoId": "6y4dY_RS_xo",
          "title": "Gold Silver Price Today:10 बजते ही सोने-चांदीके दामों में गिरावट! | Silver Price Crash | Top News",
          "description": "Gold Silver Price Today:10 बजते ही सोने-चांदीके दामों में गिरावट! | Silver Price Crash | Top ...",
          "channelTitle": "News18 MP Chhattisgarh",
          "publishedAt": "2026-02-02T04:30:06Z",
          "thumbnail": "https://i.ytimg.com/vi/6y4dY_RS_xo/hqdefault.jpg",
          "durationSeconds": 245,
          "durationFormatted": "04:05",
          "views": 19478,
          "likes": 130,
          "videoType": "VOD",
          "genre": "Traffic"
        },
        {
          "index": 2,
          "videoId": "yXR4xE_7omE",
          "title": "Gold Silver Price Crash: 11 बजते ही धड़ाम से गिरे सोने-चांदी के दाम! | Breaking | Share Market Crash",
          "description": "Gold Silver Price Crash: 11 बजते ही धड़ाम से गिरे सोने-चांदी के दाम! | Breaking | Share Market ...",
          "channelTitle": "News18 MP Chhattisgarh",
          "publishedAt": "2026-02-02T05:32:28Z",
          "thumbnail": "https://i.ytimg.com/vi/yXR4xE_7omE/hqdefault.jpg",
          "durationSeconds": 190,
          "durationFormatted": "03:10",
          "views": 10121,
          "likes": 59,
          "videoType": "VOD",
          "genre": "Traffic"
        },
        {
          "index": 3,
          "videoId": "h8SsYjVID8s",
          "title": "Gold Silver Price Crash: सोने चांदी के दाम में भारी गिरावट, खरीदने से पहले ये जरूर जान लें! | N18V",
          "description": "Gold Silver Price Crash: सोने चांदी के दाम में भारी गिरावट, खरीदने से पहले ये ...",
          "channelTitle": "News18 MP Chhattisgarh",
          "publishedAt": "2026-02-02T06:19:46Z",
          "thumbnail": "https://i.ytimg.com/vi/h8SsYjVID8s/hqdefault.jpg",
          "durationSeconds": 148,
          "durationFormatted": "02:28",
          "views": 6807,
          "likes": 67,
          "videoType": "VOD",
          "genre": "Traffic"
        },
        {
          "index": 4,
          "videoId": "y_0EXPYRAeE",
          "title": "Gold Silver Price Crash:  धड़ाम से गिरा सोना चांदी का दाम! | Gold Silver Rate Today | Top News",
          "description": "Gold Silver Price Crash: धड़ाम से गिरा सोना चांदी का दाम! | Gold Silver Rate Today | Top News ...",
          "channelTitle": "News18 MP Chhattisgarh",
          "publishedAt": "2026-02-02T07:11:21Z",
          "thumbnail": "https://i.ytimg.com/vi/y_0EXPYRAeE/hqdefault.jpg",
          "durationSeconds": 190,
          "durationFormatted": "03:10",
          "views": 6588,
          "likes": 44,
          "videoType": "VOD",
          "genre": "Traffic"
        },
        {
          "index": 5,
          "videoId": "fWSN-V3aQWo",
          "title": "Gold Silver Rate: Budget 2026 के बाद सोना-चांदी धड़ाम! आखिर क्यों औंधे मुंह गिरी कीमतें? Gold Rate",
          "description": "Gold Silver Rate: Budget 2026 के बाद सोना-चांदी धड़ाम! आखिर क्यों औंधे मुंह गिरी ...",
          "channelTitle": "NDTV MP Chhattisgarh",
          "publishedAt": "2026-02-02T01:23:51Z",
          "thumbnail": "https://i.ytimg.com/vi/fWSN-V3aQWo/hqdefault.jpg",
          "durationSeconds": 178,
          "durationFormatted": "02:58",
          "views": 148,
          "likes": 6,
          "videoType": "VOD",
          "genre": "Politics"
        }
      ],
      "latestUpdateAt": "2026-02-02T07:11:21Z"
    },
    {
      "clusterId": "world-cup",
      "topic": "World Cup",
      "videoCount": 7,
      "trendScore": 35.9,
      "topVideos": [
        {
          "index": 1,
          "videoId": "hMd17zyjaN8",
          "title": "Pakistan Boycott T20 World Cup: भारत ने पाकिस्तान को दिखाई औकात! T20 वर्ल्ड कप से होगा बाहर? | N18V",
          "description": "Pakistan Boycott T20 World Cup: भारत ने पाकिस्तान को दिखाई औकात! T20 वर्ल्ड कप से ...",
          "channelTitle": "News18 MP Chhattisgarh",
          "publishedAt": "2026-02-02T06:43:40Z",
          "thumbnail": "https://i.ytimg.com/vi/hMd17zyjaN8/hqdefault.jpg",
          "durationSeconds": 150,
          "durationFormatted": "02:30",
          "views": 1527,
          "likes": 20,
          "videoType": "VOD",
          "genre": "Events"
        },
        {
          "index": 2,
          "videoId": "8fNobyYaWLY",
          "title": "T20 World Cup : भारत के खिलाफ मैच नहीं खेलेगा पाकिस्तान, 15 फरवरी को होना है मुकाबला",
          "description": "india pakistan match t20 world cup: टी20 वर्ल्ड कप से पहले पाकिस्तान ने बड़ा फैसला ...",
          "channelTitle": "Bansal News MPCG",
          "publishedAt": "2026-02-01T15:48:00Z",
          "thumbnail": "https://i.ytimg.com/vi/8fNobyYaWLY/hqdefault.jpg",
          "durationSeconds": 263,
          "durationFormatted": "04:23",
          "views": 1238,
          "likes": 10,
          "videoType": "VOD",
          "genre": "Events"
        },
        {
          "index": 3,
          "videoId": "trDDOPCtW8g",
          "title": "T20 World Cup 2026: वर्ल्ड कप में India से नहीं खेलेगा पाकिस्तान | Pakistan वर्ल्ड कप से होगा बाहर?",
          "description": "IBC24, T20 World Cup 2026: वर्ल्ड कप में India से नहीं खेलेगा पाकिस्तान | Pakistan ...",
          "channelTitle": "IBC24",
          "publishedAt": "2026-02-02T02:30:42Z",
          "thumbnail": "https://i.ytimg.com/vi/trDDOPCtW8g/hqdefault.jpg",
          "durationSeconds": 93,
          "durationFormatted": "01:33",
          "views": 1144,
          "likes": 0,
          "videoType": "VOD",
          "genre": "Events"
        },
        {
          "index": 4,
          "videoId": "1d70SbmYgQQ",
          "title": "T20 World Cup: T-20 वर्ल्ड कप में भारत के खिलाफ नहीं खेलेगा पाकिस्तान| Breaking News | Jay Shah |",
          "description": "T20 World Cup: T-20 वर्ल्ड कप में भारत के खिलाफ नहीं खेलेगा पाकिस्तान| Breaking ...",
          "channelTitle": "News18 MP Chhattisgarh",
          "publishedAt": "2026-02-02T05:44:38Z",
          "thumbnail": "https://i.ytimg.com/vi/1d70SbmYgQQ/hqdefault.jpg",
          "durationSeconds": 320,
          "durationFormatted": "05:20",
          "views": 535,
          "likes": 3,
          "videoType": "VOD",
          "genre": "Events"
        },
        {
          "index": 5,
          "videoId": "wF2dQikr18s",
          "title": "T20 World Cup Row: पाकिस्तान को ICC की बड़ी चेतावनी! T20 वर्ल्ड कप से होगा बाहर? | Jay Shah Breaking",
          "description": "T20 World Cup Row: पाकिस्तान को ICC की बड़ी चेतावनी! T20 वर्ल्ड कप से होगा बाहर ...",
          "channelTitle": "News18 MP Chhattisgarh",
          "publishedAt": "2026-02-02T04:46:15Z",
          "thumbnail": "https://i.ytimg.com/vi/wF2dQikr18s/hqdefault.jpg",
          "durationSeconds": 323,
          "durationFormatted": "05:23",
          "views": 274,
          "likes": 4,
          "videoType": "VOD",
          "genre": "Events"
        }
      ],
      "latestUpdateAt": "2026-02-02T06:43:40Z"
    },
    {
      "clusterId": "bhaskar-budget",
      "topic": "Bhaskar Budget",
      "videoCount": 8,
      "trendScore": 35.2,
      "topVideos": [
        {
          "index": 1,
          "videoId": "5-AtgDagsMs",
          "title": "क्या और सस्ते हो जाएँगे सोने-चाँदी के दाम? | CG Bhaskar",
          "description": "क्या और सस्ते हो जाएँगे सोने-चाँदी के दाम? | CG Bhaskar Join our Whatsapp Group ...",
          "channelTitle": "CG Bhaskar",
          "publishedAt": "2026-02-01T11:21:32Z",
          "thumbnail": "https://i.ytimg.com/vi/5-AtgDagsMs/hqdefault.jpg",
          "durationSeconds": 125,
          "durationFormatted": "02:05",
          "views": 1359,
          "likes": 32,
          "videoType": "VOD",
          "genre": "General"
        },
        {
          "index": 2,
          "videoId": "rHhNNWwNta4",
          "title": "कपड़े, बीड़ी समेत ये चीजें हुई सस्ती | CG Bhaskar",
          "description": "कपड़े, बीड़ी समेत ये चीजें हुई सस्ती | CG Bhaskar Join our Whatsapp Group ...",
          "channelTitle": "CG Bhaskar",
          "publishedAt": "2026-02-01T12:30:11Z",
          "thumbnail": "https://i.ytimg.com/vi/rHhNNWwNta4/hqdefault.jpg",
          "durationSeconds": 42,
          "durationFormatted": "00:42",
          "views": 1304,
          "likes": 28,
          "videoType": "VOD",
          "genre": "General"
        },
        {
          "index": 3,
          "videoId": "GzO6cwJnC-E",
          "title": "बजट में अब Content Creators के लिए बड़ी खुशखबरी | Mohit, Aastha | CG Bhaskar",
          "description": "बजट में अब Content Creators के लिए बड़ी खुशखबरी| Mohit, Aastha | CG Bhaskar Join our Whatsapp Group ...",
          "channelTitle": "CG Bhaskar",
          "publishedAt": "2026-02-01T09:19:08Z",
          "thumbnail": "https://i.ytimg.com/vi/GzO6cwJnC-E/hqdefault.jpg",
          "durationSeconds": 53,
          "durationFormatted": "00:53",
          "views": 1269,
          "likes": 25,
          "videoType": "VOD",
          "genre": "Politics"
        },
        {
          "index": 4,
          "videoId": "e_grFQ5QogA",
          "title": "Budget 2026: व्यापारी निराश! फिर किसकी हुई चांदी ? | CG Bhaskar",
          "description": "Budget 2026: व्यापारी निराश! फिर किसकी हुई चांदी ? | CG Bhaskar Join our Whatsapp Group ...",
          "channelTitle": "CG Bhaskar",
          "publishedAt": "2026-02-01T14:30:39Z",
          "thumbnail": "https://i.ytimg.com/vi/e_grFQ5QogA/hqdefault.jpg",
          "durationSeconds": 175,
          "durationFormatted": "02:55",
          "views": 589,
          "likes": 21,
          "videoType": "VOD",
          "genre": "Politics"
        },
        {
          "index": 5,
          "videoId": "uVPXgtBa38o",
          "title": "अब बच्चों के Ideas को मिलेगी उड़ान | CG Bhaskar",
          "description": "अब बच्चों के Ideas को मिलेगी उड़ान | CG Bhaskar Join our Whatsapp Group ...",
          "channelTitle": "CG Bhaskar",
          "publishedAt": "2026-02-01T10:20:08Z",
          "thumbnail": "https://i.ytimg.com/vi/uVPXgtBa38o/hqdefault.jpg",
          "durationSeconds": 119,
          "durationFormatted": "01:59",
          "views": 406,
          "likes": 9,
          "videoType": "VOD",
          "genre": "General"
        }
      ],
      "latestUpdateAt": "2026-02-02T07:14:42Z"
    },
    {
      "clusterId": "xpress-शवरनरयण",
      "topic": "Xpress शिवरीनारायण",
      "videoCount": 4,
      "trendScore": 31.2,
      "topVideos": [
        {
          "index": 1,
          "videoId": "-Hh0fxQFmnI",
          "title": "शिवरीनारायण - पुलिस और बदमाशों के बीच हुई मुठभेड़, चली गोलियांChhattisgarh Xpress News",
          "description": "Chhattisgarh Xpress News सबसे तेज सबसे आगे विश्वसनीय न्यूज़ चैनल “छत्तीसगढ़ ...",
          "channelTitle": "Chhattisgarh Xpress News",
          "publishedAt": "2026-02-01T11:46:50Z",
          "thumbnail": "https://i.ytimg.com/vi/-Hh0fxQFmnI/hqdefault.jpg",
          "durationSeconds": 203,
          "durationFormatted": "03:23",
          "views": 7407,
          "likes": 102,
          "videoType": "VOD",
          "genre": "General"
        },
        {
          "index": 2,
          "videoId": "Xjr34v_kMmE",
          "title": "बिलासपुर - बोरिंग मशीन की हाई प्रेशर से उखड़ गया पड़ोसी का टाइल्स, देखें वीडियोCG Xpress News",
          "description": "Chhattisgarh Xpress News सबसे तेज सबसे आगे विश्वसनीय न्यूज़ चैनल “छत्तीसगढ़ ...",
          "channelTitle": "Chhattisgarh Xpress News",
          "publishedAt": "2026-02-01T12:28:34Z",
          "thumbnail": "https://i.ytimg.com/vi/Xjr34v_kMmE/hqdefault.jpg",
          "durationSeconds": 59,
          "durationFormatted": "00:59",
          "views": 712,
          "likes": 8,
          "videoType": "VOD",
          "genre": "General"
        },
        {
          "index": 3,
          "videoId": "XIHdkYFi3e4",
          "title": "जगदलपुर - देवांगन समाज ने मां परमेश्वरी महोत्सव का किया आयोजनChhattisgarh Xpress News",
          "description": "Chhattisgarh Xpress News सबसे तेज सबसे आगे विश्वसनीय न्यूज़ चैनल “छत्तीसगढ़ ...",
          "channelTitle": "Chhattisgarh Xpress News",
          "publishedAt": "2026-02-01T13:27:45Z",
          "thumbnail": "https://i.ytimg.com/vi/XIHdkYFi3e4/hqdefault.jpg",
          "durationSeconds": 153,
          "durationFormatted": "02:33",
          "views": 66,
          "likes": 1,
          "videoType": "VOD",
          "genre": "General"
        },
        {
          "index": 4,
          "videoId": "5Nl3xPZZqS0",
          "title": "सिमगा -  दामाखेड़ा के कबीर संत समागम में शामिल हुए मुख्यमंत्रीChhattisgarh Xpress News",
          "description": "Chhattisgarh Xpress News सबसे तेज सबसे आगे विश्वसनीय न्यूज़ चैनल “छत्तीसगढ़ ...",
          "channelTitle": "Chhattisgarh Xpress News",
          "publishedAt": "2026-02-02T06:42:51Z",
          "thumbnail": "https://i.ytimg.com/vi/5Nl3xPZZqS0/hqdefault.jpg",
          "durationSeconds": 140,
          "durationFormatted": "02:20",
          "views": 2,
          "likes": 1,
          "videoType": "VOD",
          "genre": "General"
        }
      ],
      "latestUpdateAt": "2026-02-02T06:42:51Z"
    },
    {
      "clusterId": "durg-करन",
      "topic": "Durg करने",
      "videoCount": 4,
      "trendScore": 31.0,
      "topVideos": [
        {
          "index": 1,
          "videoId": "x2ojz-Ad3zI",
          "title": "भिलाई 3; धर्मांतरण करने गई दो महिला गिरफ्तार, 10000 का दिया लालच?",
          "description": "bhilai #shortsfeed #trending #news #chhattisgarh #crime #durg #india #at #ytshorts #charoda #bhilainewstoday #bhilainews ...",
          "channelTitle": "CG JANMAT ",
          "publishedAt": "2026-02-01T09:02:56Z",
          "thumbnail": "https://i.ytimg.com/vi/x2ojz-Ad3zI/hqdefault.jpg",
          "durationSeconds": 127,
          "durationFormatted": "02:07",
          "views": 917,
          "likes": 23,
          "videoType": "VOD",
          "genre": "General"
        },
        {
          "index": 2,
          "videoId": "KZE6PA8Uw_w",
          "title": "चरौदा बिजली के खंभे में ठोकर, ट्रक की छत पर चढ़ा खंभा, कुम्हारी में पकड़ाया।",
          "description": "bhilai #shortsfeed #trending #news #chhattisgarh #crime #durg #at #india #ytshorts #charoda #charodanews #bhilainews ...",
          "channelTitle": "CG JANMAT ",
          "publishedAt": "2026-02-02T03:01:07Z",
          "thumbnail": "https://i.ytimg.com/vi/KZE6PA8Uw_w/hqdefault.jpg",
          "durationSeconds": 129,
          "durationFormatted": "02:09",
          "views": 334,
          "likes": 5,
          "videoType": "VOD",
          "genre": "General"
        },
        {
          "index": 3,
          "videoId": "2d2DNIsrsvo",
          "title": "Breaking; Durg पुलिस चोरी का खुलासा, घर में काम करने वाली बाई निकली मास्टरमाइंड, ",
          "description": "bhilai #shortsfeed #trending #news #chhattisgarh #crime #durg #india #at #ytshorts #bhilainews #todaynews #padmanbhpur ...",
          "channelTitle": "CG JANMAT ",
          "publishedAt": "2026-02-01T10:54:52Z",
          "thumbnail": "https://i.ytimg.com/vi/2d2DNIsrsvo/hqdefault.jpg",
          "durationSeconds": 134,
          "durationFormatted": "02:14",
          "views": 241,
          "likes": 5,
          "videoType": "VOD",
          "genre": "General"
        },
        {
          "index": 4,
          "videoId": "lEVKs9XrG7A",
          "title": "चरौदा बड़ा ह|दसा टला, शर|ब के नशे में 3 बजे गाड़ियों को रौंदा....!",
          "description": "bhilai #shortsfeed #trending #news #chhattisgarh #crime #durg #at #india #ytshorts #bhilainews #bhilai3 #charoda ...",
          "channelTitle": "CG JANMAT ",
          "publishedAt": "2026-02-02T06:47:07Z",
          "thumbnail": "https://i.ytimg.com/vi/lEVKs9XrG7A/hqdefault.jpg",
          "durationSeconds": 212,
          "durationFormatted": "03:32",
          "views": 136,
          "likes": 3,
          "videoType": "VOD",
          "genre": "General"
        }
      ],
      "latestUpdateAt": "2026-02-02T06:47:07Z"
    }
  ]
}