{
  "generatedAt": "2026-03-07T22:37:38.983142Z",
  "clusterCount": 7,
  "clusters": [
    {
      "clusterId": "public-sector-exam",
      "topic": "Public Sector Exam",
      "videoCount": 79,
      "trendScore": 61.2,
      "topVideos": [
        {
          "index": 1,
          "videoId": "23KDr99tk8k",
          "title": "Durg में अफीम की खेती करने वाला BJP नेता कौन? | Bhupesh ने क्या कह दिया | Ground Report | Yashwant",
          "description": "Durg में अफीम की खेती करने वाला BJP नेता कौन? | Bhupesh ने क्या कह दिया | Ground ...",
          "channelTitle": "Bhilai Times",
          "publishedAt": "2026-03-07T14:00:07Z",
          "thumbnail": "https://i.ytimg.com/vi/23KDr99tk8k/hqdefault.jpg",
          "durationSeconds": 1245,
          "durationFormatted": "20:45",
          "views": 36015,
          "likes": 837,
          "videoType": "VOD",
          "genre": "Politics"
        },
        {
          "index": 2,
          "videoId": "ODzMtc5NDLQ",
          "title": "7 March 2026 CG News Today | CG Fatafat News | Chhattisgarh Breaking News | CM Vishnu Deo Sai",
          "description": "7 March 2026 CG News Today | CG Fatafat News | Chhattisgarh Breaking News | CM Vishnu Deo Sai #ChhattisgarhSamachar ...",
          "channelTitle": "Republic Chhattisgarh",
          "publishedAt": "2026-03-06T23:30:09Z",
          "thumbnail": "https://i.ytimg.com/vi/ODzMtc5NDLQ/hqdefault.jpg",
          "durationSeconds": 1664,
          "durationFormatted": "27:44",
          "views": 32397,
          "likes": 312,
          "videoType": "VOD",
          "genre": "Politics"
        },
        {
          "index": 3,
          "videoId": "NQwN8rudBF4",
          "title": "Droupadi Murmu Bengal Visit: राष्ट्रपति को रिसीव करने नहीं पहुंचीं CM ममता बनर्जी तो भड़के PM मोदी!",
          "description": "Droupadi Murmu Bengal Visit: राष्ट्रपति को रिसीव करने नहीं पहुंचीं CM ममता ...",
          "channelTitle": "News18 MP Chhattisgarh",
          "publishedAt": "2026-03-07T15:25:13Z",
          "thumbnail": "https://i.ytimg.com/vi/NQwN8rudBF4/hqdefault.jpg",
          "durationSeconds": 152,
          "durationFormatted": "02:32",
          "views": 22655,
          "likes": 140,
          "videoType": "VOD",
          "genre": "Politics"
        },
        {
          "index": 4,
          "videoId": "2zXNmMKqegA",
          "title": "Bihar New CM Live Updates LIVE : CM Nitish Kumar बेटे निशांत कुमार को सौंपेंगे सत्ता | Bihar News",
          "description": "Bihar New CM Live Updates LIVE : CM Nitish Kumar बेटे निशांत कुमार को सौंपेंगे सत्ता | Bihar ...",
          "channelTitle": "News18 MP Chhattisgarh",
          "publishedAt": "2026-03-07T14:40:14Z",
          "thumbnail": "https://i.ytimg.com/vi/2zXNmMKqegA/hqdefault.jpg",
          "durationSeconds": 42549,
          "durationFormatted": "11:49:09",
          "views": 17922,
          "likes": 80,
          "videoType": "VOD",
          "genre": "Politics"
        },
        {
          "index": 5,
          "videoId": "rJ4sidpkSSg",
          "title": "Bihar New CM Updates : CM Nitish Kumar बेटे निशांत कुमार को सौंपेंगे सत्ता? | Top News | BJP | RJD",
          "description": "Bihar New CM Updates : CM Nitish Kumar बेटे निशांत कुमार को सौंपेंगे सत्ता? | Top News ...",
          "channelTitle": "News18 MP Chhattisgarh",
          "publishedAt": "2026-03-07T16:45:07Z",
          "thumbnail": "https://i.ytimg.com/vi/rJ4sidpkSSg/hqdefault.jpg",
          "durationSeconds": 815,
          "durationFormatted": "13:35",
          "views": 11200,
          "likes": 62,
          "videoType": "VOD",
          "genre": "Politics"
        }
      ],
      "latestUpdateAt": "2026-03-07T19:34:41Z"
    },
    {
      "clusterId": "iran-israel",
      "topic": "Iran Israel",
      "videoCount": 16,
      "trendScore": 54.8,
      "topVideos": [
        {
          "index": 1,
          "videoId": "0BGPfGJscoM",
          "title": "Iran-Israel War Update : ईरानी सेना के सामने नेतन्याहू का सरेंडर? | Netanyahu | Khamenei | N18G",
          "description": "Iran-Israel War Update : ईरानी सेना के सामने नेतन्याहू का सरेंडर? | Netanyahu | Khamenei ...",
          "channelTitle": "News18 MP Chhattisgarh",
          "publishedAt": "2026-03-07T16:30:00Z",
          "thumbnail": "https://i.ytimg.com/vi/0BGPfGJscoM/hqdefault.jpg",
          "durationSeconds": 327,
          "durationFormatted": "05:27",
          "views": 84182,
          "likes": 1178,
          "videoType": "VOD",
          "genre": "General"
        },
        {
          "index": 2,
          "videoId": "fOB6wh2MVpk",
          "title": "Iran Attack on Israel : सरेंडर की धमकी पर ईरान ने इजरायल में मचाई तबाही! | Top News | IRGC | N18G",
          "description": "Iran Attack on Israel : सरेंडर की धमकी पर ईरान ने इजरायल में मचाई तबाही! | Top News ...",
          "channelTitle": "News18 MP Chhattisgarh",
          "publishedAt": "2026-03-07T15:06:26Z",
          "thumbnail": "https://i.ytimg.com/vi/fOB6wh2MVpk/hqdefault.jpg",
          "durationSeconds": 995,
          "durationFormatted": "16:35",
          "views": 81895,
          "likes": 1420,
          "videoType": "VOD",
          "genre": "General"
        },
        {
          "index": 3,
          "videoId": "y5Rs-lDaf44",
          "title": "Iran Attack on Israel : ईरान से अमेरिका का हारना तय? पुतिन पर भड़क गए ट्रंप! | Top News | N18G",
          "description": "Iran Attack on Israel : ईरान से अमेरिका का हारना तय? पुतिन पर भड़क गए ट्रंप! | Top News ...",
          "channelTitle": "News18 MP Chhattisgarh",
          "publishedAt": "2026-03-07T17:15:08Z",
          "thumbnail": "https://i.ytimg.com/vi/y5Rs-lDaf44/hqdefault.jpg",
          "durationSeconds": 539,
          "durationFormatted": "08:59",
          "views": 58239,
          "likes": 2087,
          "videoType": "VOD",
          "genre": "General"
        },
        {
          "index": 4,
          "videoId": "S_8FoJD0LBY",
          "title": "Iran America War Update : Al Dhafra Airbase पर ईरान का ड्रोन अटैक, अबू धाबी-दुबई एयरपोर्ट पर तबाही ?",
          "description": "Iran America War Update : Al Dhafra Airbase पर ईरान का ड्रोन अटैक, अबू धाबी-दुबई ...",
          "channelTitle": "News18 MP Chhattisgarh",
          "publishedAt": "2026-03-07T19:35:48Z",
          "thumbnail": "https://i.ytimg.com/vi/S_8FoJD0LBY/hqdefault.jpg",
          "durationSeconds": 863,
          "durationFormatted": "14:23",
          "views": 41691,
          "likes": 1033,
          "videoType": "VOD",
          "genre": "General"
        },
        {
          "index": 5,
          "videoId": "wFryY_SQulM",
          "title": "Pakistan Petrol Price Hike: पेट्रोल-डीजल को लेकर पाक में भयंकर हाहाकार! Iran Israel War Updates ।",
          "description": "Pakistan Petrol Price Hike: पेट्रोल-डीजल को लेकर पाक में भयंकर हाहाकार! Iran Israel War ...",
          "channelTitle": "News18 MP Chhattisgarh",
          "publishedAt": "2026-03-07T15:02:27Z",
          "thumbnail": "https://i.ytimg.com/vi/wFryY_SQulM/hqdefault.jpg",
          "durationSeconds": 525,
          "durationFormatted": "08:45",
          "views": 19188,
          "likes": 73,
          "videoType": "VOD",
          "genre": "General"
        }
      ],
      "latestUpdateAt": "2026-03-07T22:29:00Z"
    },
    {
      "clusterId": "chhattisgarh-raipur",
      "topic": "Chhattisgarh Raipur",
      "videoCount": 20,
      "trendScore": 50.4,
      "topVideos": [
        {
          "index": 1,
          "videoId": "nMLdE1msMh8",
          "title": "छत्तीसगढ़ आज की मुख्य समाचार | 7 मार्च 2026 छत्तीसगढ़ की फटाफट ताजा खबरें | Chhattisgarh Samachar",
          "description": "छत्तीसगढ़ आज की मुख्य समाचार | 7 मार्च 2026 छत्तीसगढ़ की फटाफट ताजा ...",
          "channelTitle": "छत्तीसगढ़ महतारी समाचार ",
          "publishedAt": "2026-03-06T23:31:01Z",
          "thumbnail": "https://i.ytimg.com/vi/nMLdE1msMh8/hqdefault.jpg",
          "durationSeconds": 1541,
          "durationFormatted": "25:41",
          "views": 19778,
          "likes": 280,
          "videoType": "VOD",
          "genre": "General"
        },
        {
          "index": 2,
          "videoId": "MgXovQho9jI",
          "title": "08 मार्च 2026 | छत्तीसगढ़ का ताजा खबर| CG News | Raipur News Today | Chattisgarh News Hindi",
          "description": "07 मार्च 2026 | छत्तीसगढ़ का ताजा खबर| CG News | Raipur News Today | Chattisgarh News Hindi ...",
          "channelTitle": "Chhattisgarh ka awaaz 07 ",
          "publishedAt": "2026-03-06T23:30:06Z",
          "thumbnail": "https://i.ytimg.com/vi/MgXovQho9jI/hqdefault.jpg",
          "durationSeconds": 922,
          "durationFormatted": "15:22",
          "views": 12149,
          "likes": 0,
          "videoType": "VOD",
          "genre": "General"
        },
        {
          "index": 3,
          "videoId": "o-V6zUD2cqg",
          "title": "07 March 2026 छत्तीसगढ़ की ताजा खबर । CG News । Raipur News Today । Chhattisgarh News Today",
          "description": "07 March 2026 छत्तीसगढ़ की ताजा खबर । CG News । Raipur News Today । Chhattisgarh News Today ...",
          "channelTitle": "द छत्तीसगढ़ समाचार",
          "publishedAt": "2026-03-06T23:01:00Z",
          "thumbnail": "https://i.ytimg.com/vi/o-V6zUD2cqg/hqdefault.jpg",
          "durationSeconds": 946,
          "durationFormatted": "15:46",
          "views": 8765,
          "likes": 114,
          "videoType": "VOD",
          "genre": "General"
        },
        {
          "index": 4,
          "videoId": "X0zsnjVqMz4",
          "title": "07 March 2026 | Chhattisgarh Ki 25 Khabre | CG News | Raipur News Today | Chattisgarh News Hindi",
          "description": "07 March 2026 | Chhattisgarh Ki 25 Khabre | CG News | Raipur News Today | Chattisgarh News Hindi दोस्तों आप ...",
          "channelTitle": "SR Chhattisgarh",
          "publishedAt": "2026-03-07T00:36:32Z",
          "thumbnail": "https://i.ytimg.com/vi/X0zsnjVqMz4/hqdefault.jpg",
          "durationSeconds": 1088,
          "durationFormatted": "18:08",
          "views": 2242,
          "likes": 0,
          "videoType": "VOD",
          "genre": "General"
        },
        {
          "index": 5,
          "videoId": "CkhDUxtn9Y4",
          "title": "छत्तीसगढ़ के प्रसिद्ध गीतकार sunil soni के साथ सुरीला बातचीत#chhattisgarh #cgpodcast #singer#raipur",
          "description": "",
          "channelTitle": "Chhattisgarh Podcast",
          "publishedAt": "2026-03-07T07:57:09Z",
          "thumbnail": "https://i.ytimg.com/vi/CkhDUxtn9Y4/hqdefault.jpg",
          "durationSeconds": 57,
          "durationFormatted": "00:57",
          "views": 1500,
          "likes": 38,
          "videoType": "VOD",
          "genre": "Podcast"
        }
      ],
      "latestUpdateAt": "2026-03-07T19:00:26Z"
    },
    {
      "clusterId": "war-effects",
      "topic": "War Effects",
      "videoCount": 7,
      "trendScore": 38.5,
      "topVideos": [
        {
          "index": 1,
          "videoId": "_vzeijevD80",
          "title": "Middle East War Side Effects : जंग की आंच भारत में, मंहगाई और किसान संकट बढ़ा | Zee MPCG | News",
          "description": "Prime Time : कहीं मंहगाई की मार.. कहीं किसान परेशान ! मिडिल ईस्ट में वॉर.",
          "channelTitle": "Zee Madhya Pradesh Chhattisgarh",
          "publishedAt": "2026-03-07T18:00:44Z",
          "thumbnail": "https://i.ytimg.com/vi/_vzeijevD80/hqdefault.jpg",
          "durationSeconds": 259,
          "durationFormatted": "04:19",
          "views": 19093,
          "likes": 102,
          "videoType": "VOD",
          "genre": "General"
        },
        {
          "index": 2,
          "videoId": "D31u5Dy1PBI",
          "title": "Iran Vs Israel Effects : खाड़ी देशों के युद्ध का असर, रसोई तक पहुंची जंग की आंच | Zee MPCG | War",
          "description": "Prime Time : खाड़ी देशों में चल रहे युद्ध का असर, रसोई तक पहुंची.. जंग की आंच !",
          "channelTitle": "Zee Madhya Pradesh Chhattisgarh",
          "publishedAt": "2026-03-07T17:49:13Z",
          "thumbnail": "https://i.ytimg.com/vi/D31u5Dy1PBI/hqdefault.jpg",
          "durationSeconds": 246,
          "durationFormatted": "04:06",
          "views": 6542,
          "likes": 67,
          "videoType": "VOD",
          "genre": "General"
        },
        {
          "index": 3,
          "videoId": "lAOmJ8zCfsg",
          "title": "Kolkata Blast : कोलकाता में बम विस्फोट! बंद क्लब के कमरे में धमाका, कई घर तबाह | Zee MPCG | News",
          "description": "Prime Time : कोलकाता में 'बम' विस्फोट.. किसकी साजिश ? बंद क्लब के कमरे में बम ...",
          "channelTitle": "Zee Madhya Pradesh Chhattisgarh",
          "publishedAt": "2026-03-07T18:02:13Z",
          "thumbnail": "https://i.ytimg.com/vi/lAOmJ8zCfsg/hqdefault.jpg",
          "durationSeconds": 149,
          "durationFormatted": "02:29",
          "views": 695,
          "likes": 2,
          "videoType": "VOD",
          "genre": "Crime"
        },
        {
          "index": 4,
          "videoId": "LIqmqShaHUM",
          "title": "🔴LIVE : Prime Time @9 : मोहन सरकार...सौगातों की बरसात  | Latest News | Zee MPCG",
          "description": "LIVE : Prime Time @9 : मोहन सरकार...सौगातों की बरसात | Latest News | Zee MPCG #primetime@9 ...",
          "channelTitle": "Zee Madhya Pradesh Chhattisgarh",
          "publishedAt": "2026-03-07T15:25:49Z",
          "thumbnail": "https://i.ytimg.com/vi/LIqmqShaHUM/hqdefault.jpg",
          "durationSeconds": 1489,
          "durationFormatted": "24:49",
          "views": 235,
          "likes": 1,
          "videoType": "VOD",
          "genre": "General"
        },
        {
          "index": 5,
          "videoId": "88HioECLOUU",
          "title": "Vidisha Development Projects : मोहन सरकार की विदिशा में बड़ी सौगात|विकास और खेल सुविधाओं का लोकार्पण",
          "description": "Prime Time : मोहन सरकार... विकास को नई रफ्तार , विदिशा को करोड़ों की सौगात, ...",
          "channelTitle": "Zee Madhya Pradesh Chhattisgarh",
          "publishedAt": "2026-03-07T16:16:11Z",
          "thumbnail": "https://i.ytimg.com/vi/88HioECLOUU/hqdefault.jpg",
          "durationSeconds": 187,
          "durationFormatted": "03:07",
          "views": 76,
          "likes": 1,
          "videoType": "VOD",
          "genre": "Politics"
        }
      ],
      "latestUpdateAt": "2026-03-07T18:15:05Z"
    },
    {
      "clusterId": "festival",
      "topic": "Festival",
      "videoCount": 5,
      "trendScore": 37.3,
      "topVideos": [
        {
          "index": 1,
          "videoId": "ECzjS_2AsHQ",
          "title": "रायपुर में दारूवाली होली",
          "description": "cg #cgreels #cgsongs #chhattisgarh #raipur #cgnews #shorts #cgshorts #ytshorts #cgvideo #cgvideo #cgfam #cgfamily #cgviral ...",
          "channelTitle": "Thiha Chhattisgarh",
          "publishedAt": "2026-03-07T10:24:53Z",
          "thumbnail": "https://i.ytimg.com/vi/ECzjS_2AsHQ/hqdefault.jpg",
          "durationSeconds": 118,
          "durationFormatted": "01:58",
          "views": 20402,
          "likes": 411,
          "videoType": "VOD",
          "genre": "General"
        },
        {
          "index": 2,
          "videoId": "kHKuGvU5oJ0",
          "title": "🔴Shrimad Bhagwat Katha Yuvraj Pandey | Day 7 | Murai (Dhirgholi) District- Khairgarh Chhuikhadan CG",
          "description": "IBC24, Shrimad Bhagwat Katha Yuvraj Pandey LIVE | Day 7 | Murai (Dhirgholi) District-Khairgarh Chhuikhadan (Chhattisgarh) ...",
          "channelTitle": "IBC24",
          "publishedAt": "2026-03-07T19:10:14Z",
          "thumbnail": "https://i.ytimg.com/vi/kHKuGvU5oJ0/hqdefault.jpg",
          "durationSeconds": 42896,
          "durationFormatted": "11:54:56",
          "views": 1707,
          "likes": 0,
          "videoType": "VOD",
          "genre": "General"
        },
        {
          "index": 3,
          "videoId": "dhzxraka_b0",
          "title": "खामेनेई की मौत पर मातम..ईरान के युद्ध की भारत में गूंज। #iranisraelwar #middleeastwar #khameneideath",
          "description": "IBC24, खामेनेई की मौत पर मातम..ईरान के युद्ध की भारत में गूंज। #iranisraelwar ...",
          "channelTitle": "IBC24",
          "publishedAt": "2026-03-07T17:32:51Z",
          "thumbnail": "https://i.ytimg.com/vi/dhzxraka_b0/hqdefault.jpg",
          "durationSeconds": 138,
          "durationFormatted": "02:18",
          "views": 836,
          "likes": 0,
          "videoType": "VOD",
          "genre": "Crime"
        },
        {
          "index": 4,
          "videoId": "gGUnkmAUtB8",
          "title": "दुर्ग संगीत महाविद्यालय में होली की तैयारी, कार्यक्रम में रौनक ,परंपरा और संगीत का अनोखा संगम",
          "description": "chhattisgarhnews #madhyapradehnews #durgnews .",
          "channelTitle": "ITN DIGITAL+",
          "publishedAt": "2026-03-07T12:25:19Z",
          "thumbnail": "https://i.ytimg.com/vi/gGUnkmAUtB8/hqdefault.jpg",
          "durationSeconds": 53,
          "durationFormatted": "00:53",
          "views": 8,
          "likes": 1,
          "videoType": "VOD",
          "genre": "General"
        },
        {
          "index": 5,
          "videoId": "FNOYdFoLJ18",
          "title": "छुरिया: रंग, संगीत और भाईचारे की मिसाल – ध्रुव गोंड़ समाज की होली",
          "description": "chhattisgarhnews #madhyapradehnews #chhuriya .",
          "channelTitle": "ITN DIGITAL+",
          "publishedAt": "2026-03-07T11:24:52Z",
          "thumbnail": "https://i.ytimg.com/vi/FNOYdFoLJ18/hqdefault.jpg",
          "durationSeconds": 50,
          "durationFormatted": "00:50",
          "views": 2,
          "likes": 1,
          "videoType": "VOD",
          "genre": "General"
        }
      ],
      "latestUpdateAt": "2026-03-07T19:10:14Z"
    },
    {
      "clusterId": "bhaskar-xpose",
      "topic": "Bhaskar XPOSE",
      "videoCount": 4,
      "trendScore": 34.4,
      "topVideos": [
        {
          "index": 1,
          "videoId": "Q3ymmBZXWoE",
          "title": "रिकेश सेन के खिलाफबड़ी साजिश कई नेता होंगे XPOSE!| CG Bhaskar",
          "description": "रिकेश सेन के खिलाफबड़ी साजिश कई नेता होंगे XPOSE!| CG Bhaskar Join our Whatsapp Group ...",
          "channelTitle": "CG Bhaskar",
          "publishedAt": "2026-03-07T13:56:02Z",
          "thumbnail": "https://i.ytimg.com/vi/Q3ymmBZXWoE/hqdefault.jpg",
          "durationSeconds": 84,
          "durationFormatted": "01:24",
          "views": 1619,
          "likes": 56,
          "videoType": "VOD",
          "genre": "Politics"
        },
        {
          "index": 2,
          "videoId": "FY9w_l-cZ1s",
          "title": "मूकबधिर दिव्यांगों के लिए नौकरी का सुनहरा मौका",
          "description": "मूकबधिर दिव्यांगों के लिए नौकरी का सुनहरा मौका Join our Whatsapp Group ...",
          "channelTitle": "CG Bhaskar",
          "publishedAt": "2026-03-07T09:30:15Z",
          "thumbnail": "https://i.ytimg.com/vi/FY9w_l-cZ1s/hqdefault.jpg",
          "durationSeconds": 72,
          "durationFormatted": "01:12",
          "views": 1297,
          "likes": 44,
          "videoType": "VOD",
          "genre": "Jobs"
        },
        {
          "index": 3,
          "videoId": "h8nK8fvnqp0",
          "title": "Smart Pole या Showpiece? | CG Bhaskar",
          "description": "Smart Pole या Showpiece? Join our Whatsapp Group https://chat.whatsapp.com/Der1Etf9PedCNRo3cUZZxx Follow us on ...",
          "channelTitle": "CG Bhaskar",
          "publishedAt": "2026-03-07T12:41:08Z",
          "thumbnail": "https://i.ytimg.com/vi/h8nK8fvnqp0/hqdefault.jpg",
          "durationSeconds": 89,
          "durationFormatted": "01:29",
          "views": 998,
          "likes": 27,
          "videoType": "VOD",
          "genre": "General"
        },
        {
          "index": 4,
          "videoId": "2a3oFG5jiI4",
          "title": "पत्रकार छत्रपति हत्याकांड में बरी हुआ राम रहीम  | CG Bhaskar",
          "description": "पत्रकार छत्रपति हत्याकांड में बरी हुआ राम रहीम Join our Whatsapp Group ...",
          "channelTitle": "CG Bhaskar",
          "publishedAt": "2026-03-07T08:03:00Z",
          "thumbnail": "https://i.ytimg.com/vi/2a3oFG5jiI4/hqdefault.jpg",
          "durationSeconds": 83,
          "durationFormatted": "01:23",
          "views": 666,
          "likes": 18,
          "videoType": "VOD",
          "genre": "General"
        }
      ],
      "latestUpdateAt": "2026-03-07T13:56:02Z"
    },
    {
      "clusterId": "रजनदगव-सकम",
      "topic": "राजनांदगांव सुकमा",
      "videoCount": 11,
      "trendScore": 26.8,
      "topVideos": [
        {
          "index": 1,
          "videoId": "Jt6tqEU1jq0",
          "title": "सुकमा: बाइक से दुर्गम इलाकों का दौरा, कलेक्टर-एसपी ने सुनी ग्रामीणों की समस्या",
          "description": "chhattisgarhnews #madhyapradehnews #sukma .",
          "channelTitle": "ITN DIGITAL+",
          "publishedAt": "2026-03-07T12:27:51Z",
          "thumbnail": "https://i.ytimg.com/vi/Jt6tqEU1jq0/hqdefault.jpg",
          "durationSeconds": 69,
          "durationFormatted": "01:09",
          "views": 16,
          "likes": 0,
          "videoType": "VOD",
          "genre": "General"
        },
        {
          "index": 2,
          "videoId": "WRq81wY8hxw",
          "title": "राजनांदगांव: ई-रिक्शा लोन में अड़चन, बेरोजगार हितग्राही परेशान,कलेक्टर से लगाई गुहार",
          "description": "chhattisgarhnews #madhyapradehnews #rajnandgaon .",
          "channelTitle": "ITN DIGITAL+",
          "publishedAt": "2026-03-07T11:27:42Z",
          "thumbnail": "https://i.ytimg.com/vi/WRq81wY8hxw/hqdefault.jpg",
          "durationSeconds": 57,
          "durationFormatted": "00:57",
          "views": 13,
          "likes": 0,
          "videoType": "VOD",
          "genre": "General"
        },
        {
          "index": 3,
          "videoId": "cOB5ut8kKSQ",
          "title": "दुर्ग में महिला दिवस समारोह 8 मार्च को राजेंद्र पार्क में महिलाओं के सम्मान का भव्य आयोजन",
          "description": "chhattisgarhnews #madhyapradehnews #durgnews .",
          "channelTitle": "ITN DIGITAL+",
          "publishedAt": "2026-03-07T12:26:39Z",
          "thumbnail": "https://i.ytimg.com/vi/cOB5ut8kKSQ/hqdefault.jpg",
          "durationSeconds": 55,
          "durationFormatted": "00:55",
          "views": 11,
          "likes": 0,
          "videoType": "VOD",
          "genre": "Events"
        },
        {
          "index": 4,
          "videoId": "cNeZhoHuDXY",
          "title": "भिलाई में 23,935 घरों का सर्वे, मच्छरों पर सख्ती मच्छर जनित बीमारियों पर निगम का एक्शन मोड",
          "description": "chhattisgarhnews #madhyapradehnews #bhilainews .",
          "channelTitle": "ITN DIGITAL+",
          "publishedAt": "2026-03-07T13:07:00Z",
          "thumbnail": "https://i.ytimg.com/vi/cNeZhoHuDXY/hqdefault.jpg",
          "durationSeconds": 65,
          "durationFormatted": "01:05",
          "views": 8,
          "likes": 0,
          "videoType": "VOD",
          "genre": "General"
        },
        {
          "index": 5,
          "videoId": "gFJSNh4pBEE",
          "title": "अंबिकापुर: लाखों रुपये बैंक में अटके, नकदी कमी से नाराजगी धान बेचने आए किसान बैंक में घंटों खड़े",
          "description": "chhattisgarhnews #madhyapradehnews #ambikapur .",
          "channelTitle": "ITN DIGITAL+",
          "publishedAt": "2026-03-07T10:53:10Z",
          "thumbnail": "https://i.ytimg.com/vi/gFJSNh4pBEE/hqdefault.jpg",
          "durationSeconds": 147,
          "durationFormatted": "02:27",
          "views": 6,
          "likes": 0,
          "videoType": "VOD",
          "genre": "Politics"
        }
      ],
      "latestUpdateAt": "2026-03-07T13:07:00Z"
    }
  ]
}